<chart labelDisplay='none'
	bgColor='FFF1E0'
	bgAlpha= '100'
	showBorder= '0'
	BorderColor = 'd7cec5'
	BorderAlpha = '100'
	adjustDiv='0'
	showYAxisValues='1'
	setAdaptiveYMin='1'
	showValues='0' 
	decimals='2' 
	formatNumberScale='0' 
	decimalSeparator=',' 
	thousandSeparator='.' 
	connectNullData='1'
	paletteColors='386ab0,834946,8f781c,d89839,852662' 
	drawAnchors='1' 
	anchorRadius='1'
	anchorBgAlpha ='0' 
	lineThickness ='3'
	animation='1'
	showLabels='1'
	showPlotBorder='0'
	canvasPlotThickness='1'
	canvasBgColor ='FFF1E0'
	canvasBgAngle ='90'
	canvasBorderThickness='1'
	canvasBorderColor='C6C6C6'
	PlotBorderColor='ffffff'
	plotGradientColor='000000'
	plotFillAngle = '90'
	plotFillRatio='99'
	plotFillAlpha='100,80'
	useRoundEdges='0'
	showAlternateHGridColor='0'
	alternateVGridAlpha='50'
	alternateVGridColor='A4A4A4'
	divLineIsColor='4C4C4C'
	divLineThickness='1'
	divLineIsDashed='1' divLineDashLen='1' divLineDashGap='3'
	vDivLineIsDashed='0'
	vDivLineColor ='d6d6d6'
	baseFont='Arial'
	baseFontColor='4C4C4C' 
	outCnvBaseFontSize='10'
	legendBorderThickness ='0'
	legendBorderColor = 'ffffff'
	legendShadow ='0'
	chartLeftMargin='0'
	chartRightMargin='1'
	chartTopMargin='8'
	chartBottomMargin='0'
	showShadow='0'
	><categories><category showLabel='0' label='02/01/2007' /><category showLabel='0' label='05/01/2007' /><category showLabel='0' label='15/01/2007' /><vLine color='edebeb' thickness='1' dashed ='0' dashLen ='1' dashGap ='3' /><category showLabel='0' label='26/02/2007' /><vLine color='edebeb' thickness='1' dashed ='0' dashLen ='1' dashGap ='3' /><category showLabel='0' label='05/03/2007' /><category showLabel='0' label='23/03/2007' /><category showLabel='0' label='26/03/2007' /><category showLabel='0' label='28/03/2007' /><vLine color='edebeb' thickness='1' dashed ='0' dashLen ='1' dashGap ='3' /><category showLabel='0' label='16/04/2007' /><vLine color='edebeb' thickness='1' dashed ='0' dashLen ='1' dashGap ='3' /><category showLabel='0' label='30/05/2007' /><vLine color='edebeb' thickness='1' dashed ='0' dashLen ='1' dashGap ='3' /><category showLabel='0' label='05/06/2007' /><category showLabel='0' label='12/06/2007' /><category showLabel='0' label='13/06/2007' /><category showLabel='0' label='20/06/2007' /><vLine color='edebeb' thickness='1' dashed ='0' dashLen ='1' dashGap ='3' /><category showLabel='0' label='13/07/2007' /><category showLabel='0' label='17/07/2007' /><vLine color='edebeb' thickness='1' dashed ='0' dashLen ='1' dashGap ='3' /><category showLabel='0' label='28/08/2007' /><category showLabel='0' label='31/08/2007' /><vLine color='edebeb' thickness='1' dashed ='0' dashLen ='1' dashGap ='3' /><category showLabel='0' label='03/09/2007' /><category showLabel='0' label='17/09/2007' /><vLine color='edebeb' thickness='1' dashed ='0' dashLen ='1' dashGap ='3' /><category showLabel='0' label='09/10/2007' /><category showLabel='0' label='30/10/2007' /><vLine color='edebeb' thickness='1' dashed ='0' dashLen ='1' dashGap ='3' /><category showLabel='0' label='01/11/2007' /><category showLabel='0' label='21/11/2007' /><category showLabel='0' label='22/11/2007' /><vLine color='edebeb' thickness='1' dashed ='0' dashLen ='1' dashGap ='3' /><category showLabel='0' label='12/12/2007' /><category showLabel='0' label='13/12/2007' /><vLine color='c6c6c6' thickness='1' dashed ='0' dashLen ='1' dashGap ='3' /><category showLabel='1' label='2008' /><category showLabel='0' label='25/01/2008' /><vLine color='edebeb' thickness='1' dashed ='0' dashLen ='1' dashGap ='3' /><category showLabel='0' label='08/02/2008' /><category showLabel='0' label='11/02/2008' /><vLine color='edebeb' thickness='1' dashed ='0' dashLen ='1' dashGap ='3' /><category showLabel='0' label='05/03/2008' /><category showLabel='0' label='19/03/2008' /><category showLabel='0' label='31/03/2008' /><vLine color='edebeb' thickness='1' dashed ='0' dashLen ='1' dashGap ='3' /><category showLabel='0' label='02/04/2008' /><category showLabel='0' label='30/04/2008' /><vLine color='edebeb' thickness='1' dashed ='0' dashLen ='1' dashGap ='3' /><category showLabel='0' label='02/05/2008' /><category showLabel='0' label='06/05/2008' /><category showLabel='0' label='22/05/2008' /><category showLabel='0' label='28/05/2008' /><vLine color='edebeb' thickness='1' dashed ='0' dashLen ='1' dashGap ='3' /><category showLabel='0' label='18/07/2008' /><category showLabel='0' label='21/07/2008' /><category showLabel='0' label='22/07/2008' /><category showLabel='0' label='23/07/2008' /><category showLabel='0' label='30/07/2008' /><vLine color='edebeb' thickness='1' dashed ='0' dashLen ='1' dashGap ='3' /><category showLabel='0' label='04/09/2008' /><category showLabel='0' label='17/09/2008' /><vLine color='edebeb' thickness='1' dashed ='0' dashLen ='1' dashGap ='3' /><category showLabel='0' label='10/10/2008' /><category showLabel='0' label='13/10/2008' /><category showLabel='0' label='14/10/2008' /><category showLabel='0' label='17/10/2008' /><vLine color='edebeb' thickness='1' dashed ='0' dashLen ='1' dashGap ='3' /><category showLabel='0' label='12/11/2008' /><category showLabel='0' label='21/11/2008' /><vLine color='edebeb' thickness='1' dashed ='0' dashLen ='1' dashGap ='3' /><category showLabel='0' label='30/12/2008' /><vLine color='c6c6c6' thickness='1' dashed ='0' dashLen ='1' dashGap ='3' /><category showLabel='1' label='2009' /><category showLabel='0' label='06/01/2009' /><category showLabel='0' label='14/01/2009' /><vLine color='edebeb' thickness='1' dashed ='0' dashLen ='1' dashGap ='3' /><category showLabel='0' label='09/02/2009' /><vLine color='edebeb' thickness='1' dashed ='0' dashLen ='1' dashGap ='3' /><category showLabel='0' label='19/03/2009' /><category showLabel='0' label='20/03/2009' /><category showLabel='0' label='23/03/2009' /><category showLabel='0' label='30/03/2009' /><vLine color='edebeb' thickness='1' dashed ='0' dashLen ='1' dashGap ='3' /><category showLabel='0' label='07/05/2009' /><vLine color='edebeb' thickness='1' dashed ='0' dashLen ='1' dashGap ='3' /><category showLabel='0' label='03/06/2009' /><category showLabel='0' label='08/06/2009' /><category showLabel='0' label='10/06/2009' /><category showLabel='0' label='11/06/2009' /><category showLabel='0' label='22/06/2009' /><vLine color='edebeb' thickness='1' dashed ='0' dashLen ='1' dashGap ='3' /><category showLabel='0' label='20/07/2009' /><category showLabel='0' label='31/07/2009' /><vLine color='edebeb' thickness='1' dashed ='0' dashLen ='1' dashGap ='3' /><category showLabel='0' label='14/08/2009' /><category showLabel='0' label='28/08/2009' /><category showLabel='0' label='31/08/2009' /><vLine color='edebeb' thickness='1' dashed ='0' dashLen ='1' dashGap ='3' /><category showLabel='0' label='04/09/2009' /><category showLabel='0' label='17/09/2009' /><vLine color='edebeb' thickness='1' dashed ='0' dashLen ='1' dashGap ='3' /><category showLabel='0' label='02/10/2009' /><category showLabel='0' label='09/10/2009' /><vLine color='edebeb' thickness='1' dashed ='0' dashLen ='1' dashGap ='3' /><category showLabel='0' label='19/11/2009' /><category showLabel='0' label='20/11/2009' /><vLine color='c6c6c6' thickness='1' dashed ='0' dashLen ='1' dashGap ='3' /><category showLabel='1' label='2010' /><category showLabel='0' label='11/01/2010' /><category showLabel='0' label='14/01/2010' /><vLine color='edebeb' thickness='1' dashed ='0' dashLen ='1' dashGap ='3' /><category showLabel='0' label='02/02/2010' /><category showLabel='0' label='08/02/2010' /><category showLabel='0' label='09/02/2010' /><category showLabel='0' label='19/02/2010' /><vLine color='edebeb' thickness='1' dashed ='0' dashLen ='1' dashGap ='3' /><category showLabel='0' label='06/04/2010' /><category showLabel='0' label='14/04/2010' /><category showLabel='0' label='22/04/2010' /><category showLabel='0' label='30/04/2010' /><vLine color='edebeb' thickness='1' dashed ='0' dashLen ='1' dashGap ='3' /><category showLabel='0' label='03/05/2010' /><category showLabel='0' label='17/05/2010' /><category showLabel='0' label='25/05/2010' /><category showLabel='0' label='28/05/2010' /><vLine color='edebeb' thickness='1' dashed ='0' dashLen ='1' dashGap ='3' /><category showLabel='0' label='01/07/2010' /><category showLabel='0' label='20/07/2010' /><category showLabel='0' label='21/07/2010' /><vLine color='edebeb' thickness='1' dashed ='0' dashLen ='1' dashGap ='3' /><category showLabel='0' label='23/08/2010' /><category showLabel='0' label='25/08/2010' /><vLine color='edebeb' thickness='1' dashed ='0' dashLen ='1' dashGap ='3' /><category showLabel='0' label='30/09/2010' /><vLine color='edebeb' thickness='1' dashed ='0' dashLen ='1' dashGap ='3' /><category showLabel='0' label='06/10/2010' /><category showLabel='0' label='08/10/2010' /><category showLabel='0' label='11/10/2010' /><category showLabel='0' label='15/10/2010' /><vLine color='edebeb' thickness='1' dashed ='0' dashLen ='1' dashGap ='3' /><category showLabel='0' label='16/11/2010' /><vLine color='edebeb' thickness='1' dashed ='0' dashLen ='1' dashGap ='3' /><category showLabel='0' label='14/12/2010' /><category showLabel='0' label='15/12/2010' /><category showLabel='0' label='29/12/2010' /><category showLabel='0' label='30/12/2010' /><vLine color='c6c6c6' thickness='1' dashed ='0' dashLen ='1' dashGap ='3' /><category showLabel='1' label='2011' /><vLine color='edebeb' thickness='1' dashed ='0' dashLen ='1' dashGap ='3' /><category showLabel='0' label='03/02/2011' /><vLine color='edebeb' thickness='1' dashed ='0' dashLen ='1' dashGap ='3' /><category showLabel='0' label='09/03/2011' /><category showLabel='0' label='16/03/2011' /><category showLabel='0' label='18/03/2011' /><category showLabel='0' label='21/03/2011' /><vLine color='edebeb' thickness='1' dashed ='0' dashLen ='1' dashGap ='3' /><category showLabel='0' label='01/04/2011' /><category showLabel='0' label='06/04/2011' /><vLine color='edebeb' thickness='1' dashed ='0' dashLen ='1' dashGap ='3' /><category showLabel='0' label='07/06/2011' /><category showLabel='0' label='08/06/2011' /><category showLabel='0' label='09/06/2011' /><category showLabel='0' label='10/06/2011' /><category showLabel='0' label='14/06/2011' /><vLine color='edebeb' thickness='1' dashed ='0' dashLen ='1' dashGap ='3' /><category showLabel='0' label='18/07/2011' /><category showLabel='0' label='19/07/2011' /><vLine color='edebeb' thickness='1' dashed ='0' dashLen ='1' dashGap ='3' /><category showLabel='0' label='19/08/2011' /><category showLabel='0' label='29/08/2011' /><category showLabel='0' label='30/08/2011' /><vLine color='edebeb' thickness='1' dashed ='0' dashLen ='1' dashGap ='3' /><category showLabel='0' label='05/09/2011' /><vLine color='edebeb' thickness='1' dashed ='0' dashLen ='1' dashGap ='3' /><category showLabel='0' label='04/10/2011' /><category showLabel='0' label='28/10/2011' /><vLine color='edebeb' thickness='1' dashed ='0' dashLen ='1' dashGap ='3' /><category showLabel='0' label='11/11/2011' /><category showLabel='0' label='18/11/2011' /><category showLabel='0' label='21/11/2011' /><category showLabel='0' label='24/11/2011' /><vLine color='edebeb' thickness='1' dashed ='0' dashLen ='1' dashGap ='3' /><category showLabel='0' label='19/12/2011' /><vLine color='c6c6c6' thickness='1' dashed ='0' dashLen ='1' dashGap ='3' /><category showLabel='1' label='2012' /><vLine color='edebeb' thickness='1' dashed ='0' dashLen ='1' dashGap ='3' /><category showLabel='0' label='06/02/2012' /><category showLabel='0' label='07/02/2012' /><category showLabel='0' label='08/02/2012' /><vLine color='edebeb' thickness='1' dashed ='0' dashLen ='1' dashGap ='3' /><category showLabel='0' label='09/03/2012' /><category showLabel='0' label='16/03/2012' /><category showLabel='0' label='22/03/2012' /><vLine color='edebeb' thickness='1' dashed ='0' dashLen ='1' dashGap ='3' /><category showLabel='0' label='23/04/2012' /><category showLabel='0' label='27/04/2012' /><category showLabel='0' label='30/04/2012' /><vLine color='edebeb' thickness='1' dashed ='0' dashLen ='1' dashGap ='3' /><category showLabel='0' label='04/05/2012' /><category showLabel='0' label='22/05/2012' /><vLine color='edebeb' thickness='1' dashed ='0' dashLen ='1' dashGap ='3' /><category showLabel='0' label='01/06/2012' /><vLine color='edebeb' thickness='1' dashed ='0' dashLen ='1' dashGap ='3' /><category showLabel='0' label='12/07/2012' /><category showLabel='0' label='18/07/2012' /><category showLabel='0' label='19/07/2012' /><category showLabel='0' label='25/07/2012' /><vLine color='edebeb' thickness='1' dashed ='0' dashLen ='1' dashGap ='3' /><category showLabel='0' label='08/08/2012' /><vLine color='edebeb' thickness='1' dashed ='0' dashLen ='1' dashGap ='3' /><category showLabel='0' label='14/09/2012' /><category showLabel='0' label='24/09/2012' /><vLine color='edebeb' thickness='1' dashed ='0' dashLen ='1' dashGap ='3' /><category showLabel='0' label='05/10/2012' /><category showLabel='0' label='08/10/2012' /><category showLabel='0' label='22/10/2012' /><category showLabel='0' label='24/10/2012' /><vLine color='edebeb' thickness='1' dashed ='0' dashLen ='1' dashGap ='3' /><category showLabel='0' label='13/11/2012' /><vLine color='edebeb' thickness='1' dashed ='0' dashLen ='1' dashGap ='3' /><category showLabel='0' label='04/12/2012' /><category showLabel='0' label='24/12/2012' /><category showLabel='0' label='27/12/2012' /><category showLabel='0' label='28/12/2012' /><vLine color='c6c6c6' thickness='1' dashed ='0' dashLen ='1' dashGap ='3' /><category showLabel='1' label='2013' /><vLine color='edebeb' thickness='1' dashed ='0' dashLen ='1' dashGap ='3' /><category showLabel='0' label='22/02/2013' /><category showLabel='0' label='27/02/2013' /><vLine color='edebeb' thickness='1' dashed ='0' dashLen ='1' dashGap ='3' /><category showLabel='0' label='15/03/2013' /><category showLabel='0' label='18/03/2013' /><vLine color='edebeb' thickness='1' dashed ='0' dashLen ='1' dashGap ='3' /><category showLabel='0' label='05/04/2013' /><category showLabel='0' label='11/04/2013' /><category showLabel='0' label='24/04/2013' /><category showLabel='0' label='29/04/2013' /><vLine color='edebeb' thickness='1' dashed ='0' dashLen ='1' dashGap ='3' /><category showLabel='0' label='06/06/2013' /><category showLabel='0' label='07/06/2013' /><category showLabel='0' label='17/06/2013' /><vLine color='edebeb' thickness='1' dashed ='0' dashLen ='1' dashGap ='3' /><category showLabel='0' label='30/07/2013' /><vLine color='edebeb' thickness='1' dashed ='0' dashLen ='1' dashGap ='3' /><category showLabel='0' label='06/08/2013' /><category showLabel='0' label='12/08/2013' /><category showLabel='0' label='26/08/2013' /><category showLabel='0' label='27/08/2013' /><category showLabel='0' label='30/08/2013' /><vLine color='edebeb' thickness='1' dashed ='0' dashLen ='1' dashGap ='3' /><category showLabel='0' label='20/09/2013' /><vLine color='edebeb' thickness='1' dashed ='0' dashLen ='1' dashGap ='3' /><category showLabel='0' label='10/10/2013' /><vLine color='edebeb' thickness='1' dashed ='0' dashLen ='1' dashGap ='3' /><category showLabel='0' label='06/11/2013' /><category showLabel='0' label='15/11/2013' /><category showLabel='0' label='18/11/2013' /><vLine color='edebeb' thickness='1' dashed ='0' dashLen ='1' dashGap ='3' /><category showLabel='0' label='16/12/2013' /><category showLabel='0' label='18/12/2013' /><category showLabel='0' label='30/12/2013' /><vLine color='c6c6c6' thickness='1' dashed ='0' dashLen ='1' dashGap ='3' /><category showLabel='1' label='2014' /><vLine color='edebeb' thickness='1' dashed ='0' dashLen ='1' dashGap ='3' /><category showLabel='0' label='04/02/2014' /><category showLabel='0' label='05/02/2014' /><vLine color='edebeb' thickness='1' dashed ='0' dashLen ='1' dashGap ='3' /><category showLabel='0' label='03/03/2014' /><category showLabel='0' label='14/03/2014' /><vLine color='edebeb' thickness='1' dashed ='0' dashLen ='1' dashGap ='3' /><category showLabel='0' label='15/04/2014' /><category showLabel='0' label='17/04/2014' /><category showLabel='0' label='25/04/2014' /><category showLabel='0' label='28/04/2014' /><category showLabel='0' label='29/04/2014' /><vLine color='edebeb' thickness='1' dashed ='0' dashLen ='1' dashGap ='3' /><category showLabel='0' label='05/05/2014' /><vLine color='edebeb' thickness='1' dashed ='0' dashLen ='1' dashGap ='3' /><category showLabel='0' label='23/06/2014' /><category showLabel='0' label='26/06/2014' /><vLine color='edebeb' thickness='1' dashed ='0' dashLen ='1' dashGap ='3' /><category showLabel='0' label='16/07/2014' /><category showLabel='0' label='17/07/2014' /><category showLabel='0' label='23/07/2014' /><vLine color='edebeb' thickness='1' dashed ='0' dashLen ='1' dashGap ='3' /><category showLabel='0' label='07/08/2014' /><vLine color='edebeb' thickness='1' dashed ='0' dashLen ='1' dashGap ='3' /><category showLabel='0' label='05/09/2014' /><vLine color='edebeb' thickness='1' dashed ='0' dashLen ='1' dashGap ='3' /><category showLabel='0' label='02/10/2014' /><category showLabel='0' label='03/10/2014' /><category showLabel='0' label='06/10/2014' /><category showLabel='0' label='16/10/2014' /><category showLabel='0' label='17/10/2014' /><vLine color='edebeb' thickness='1' dashed ='0' dashLen ='1' dashGap ='3' /><category showLabel='0' label='21/11/2014' /><vLine color='edebeb' thickness='1' dashed ='0' dashLen ='1' dashGap ='3' /><category showLabel='0' label='15/12/2014' /><category showLabel='0' label='24/12/2014' /><category showLabel='0' label='29/12/2014' /><vLine color='c6c6c6' thickness='1' dashed ='0' dashLen ='1' dashGap ='3' /><category showLabel='1' label='2015' /><category showLabel='0' label='20/01/2015' /><category showLabel='0' label='27/01/2015' /><vLine color='edebeb' thickness='1' dashed ='0' dashLen ='1' dashGap ='3' /><category showLabel='0' label='12/03/2015' /><category showLabel='0' label='16/03/2015' /><category showLabel='0' label='17/03/2015' /><vLine color='edebeb' thickness='1' dashed ='0' dashLen ='1' dashGap ='3' /><category showLabel='0' label='07/04/2015' /><category showLabel='0' label='08/04/2015' /><category showLabel='0' label='20/04/2015' /><vLine color='edebeb' thickness='1' dashed ='0' dashLen ='1' dashGap ='3' /><category showLabel='0' label='02/06/2015' /><category showLabel='0' label='05/06/2015' /><category showLabel='0' label='08/06/2015' /><category showLabel='0' label='09/06/2015' /><vLine color='edebeb' thickness='1' dashed ='0' dashLen ='1' dashGap ='3' /><category showLabel='0' label='02/07/2015' /><vLine color='edebeb' thickness='1' dashed ='0' dashLen ='1' dashGap ='3' /><category showLabel='0' label='03/08/2015' /><category showLabel='0' label='24/08/2015' /><category showLabel='0' label='25/08/2015' /><category showLabel='0' label='26/08/2015' /><category showLabel='0' label='28/08/2015' /><vLine color='edebeb' thickness='1' dashed ='0' dashLen ='1' dashGap ='3' /><category showLabel='0' label='28/09/2015' /><vLine color='edebeb' thickness='1' dashed ='0' dashLen ='1' dashGap ='3' /><category showLabel='0' label='09/10/2015' /><vLine color='edebeb' thickness='1' dashed ='0' dashLen ='1' dashGap ='3' /><category showLabel='0' label='04/11/2015' /><category showLabel='0' label='13/11/2015' /><category showLabel='0' label='16/11/2015' /><category showLabel='0' label='25/11/2015' /><category showLabel='0' label='30/11/2015' /><vLine color='edebeb' thickness='1' dashed ='0' dashLen ='1' dashGap ='3' /><category showLabel='0' label='29/12/2015' /><vLine color='c6c6c6' thickness='1' dashed ='0' dashLen ='1' dashGap ='3' /><category showLabel='1' label='2016' /><vLine color='edebeb' thickness='1' dashed ='0' dashLen ='1' dashGap ='3' /><category showLabel='0' label='03/02/2016' /><category showLabel='0' label='04/02/2016' /><category showLabel='0' label='05/02/2016' /><category showLabel='0' label='10/02/2016' /><category showLabel='0' label='15/02/2016' /><category showLabel='0' label='17/02/2016' /><vLine color='edebeb' thickness='1' dashed ='0' dashLen ='1' dashGap ='3' /><category showLabel='0' label='22/04/2016' /><category showLabel='0' label='25/04/2016' /><category showLabel='0' label='26/04/2016' /><vLine color='edebeb' thickness='1' dashed ='0' dashLen ='1' dashGap ='3' /><category showLabel='0' label='12/05/2016' /><category showLabel='0' label='17/05/2016' /><vLine color='edebeb' thickness='1' dashed ='0' dashLen ='1' dashGap ='3' /><category showLabel='0' label='27/06/2016' /><vLine color='edebeb' thickness='1' dashed ='0' dashLen ='1' dashGap ='3' /><category showLabel='0' label='14/07/2016' /><category showLabel='0' label='15/07/2016' /><category showLabel='0' label='26/07/2016' /><vLine color='edebeb' thickness='1' dashed ='0' dashLen ='1' dashGap ='3' /><category showLabel='0' label='18/08/2016' /><category showLabel='0' label='22/08/2016' /><vLine color='edebeb' thickness='1' dashed ='0' dashLen ='1' dashGap ='3' /><category showLabel='0' label='30/09/2016' /><vLine color='edebeb' thickness='1' dashed ='0' dashLen ='1' dashGap ='3' /><category showLabel='0' label='03/10/2016' /><category showLabel='0' label='04/10/2016' /><category showLabel='0' label='12/10/2016' /><category showLabel='0' label='14/10/2016' /><vLine color='edebeb' thickness='1' dashed ='0' dashLen ='1' dashGap ='3' /><category showLabel='0' label='11/11/2016' /><vLine color='edebeb' thickness='1' dashed ='0' dashLen ='1' dashGap ='3' /><category showLabel='0' label='22/12/2016' /><category showLabel='0' label='23/12/2016' /><category showLabel='0' label='27/12/2016' /><category showLabel='0' label='28/12/2016' /><vLine color='c6c6c6' thickness='1' dashed ='0' dashLen ='1' dashGap ='3' /><category showLabel='1' label='2017' /><vLine color='edebeb' thickness='1' dashed ='0' dashLen ='1' dashGap ='3' /><category showLabel='0' label='27/02/2017' /><vLine color='edebeb' thickness='1' dashed ='0' dashLen ='1' dashGap ='3' /><category showLabel='0' label='06/03/2017' /><category showLabel='0' label='14/03/2017' /><category showLabel='0' label='15/03/2017' /><category showLabel='0' label='21/03/2017' /><vLine color='edebeb' thickness='1' dashed ='0' dashLen ='1' dashGap ='3' /><category showLabel='0' label='12/04/2017' /><vLine color='edebeb' thickness='1' dashed ='0' dashLen ='1' dashGap ='3' /><category showLabel='0' label='02/05/2017' /><category showLabel='0' label='08/05/2017' /><vLine color='edebeb' thickness='1' dashed ='0' dashLen ='1' dashGap ='3' /><category showLabel='0' label='02/06/2017' /><category showLabel='0' label='05/06/2017' /><category showLabel='0' label='30/06/2017' /><vLine color='edebeb' thickness='1' dashed ='0' dashLen ='1' dashGap ='3' /><category showLabel='0' label='14/07/2017' /><vLine color='edebeb' thickness='1' dashed ='0' dashLen ='1' dashGap ='3' /><category showLabel='0' label='15/08/2017' /><category showLabel='0' label='17/08/2017' /><category showLabel='0' label='23/08/2017' /><category showLabel='0' label='24/08/2017' /><vLine color='edebeb' thickness='1' dashed ='0' dashLen ='1' dashGap ='3' /><category showLabel='0' label='01/09/2017' /><category showLabel='0' label='06/09/2017' /><category showLabel='0' label='26/09/2017' /><vLine color='edebeb' thickness='1' dashed ='0' dashLen ='1' dashGap ='3' /><category showLabel='0' label='12/10/2017' /><vLine color='edebeb' thickness='1' dashed ='0' dashLen ='1' dashGap ='3' /><category showLabel='0' label='10/11/2017' /><category showLabel='0' label='13/11/2017' /><vLine color='edebeb' thickness='1' dashed ='0' dashLen ='1' dashGap ='3' /><category showLabel='0' label='22/12/2017' /><vLine color='c6c6c6' thickness='1' dashed ='0' dashLen ='1' dashGap ='3' /><category showLabel='1' label='2018' /><category showLabel='0' label='30/01/2018' /><vLine color='edebeb' thickness='1' dashed ='0' dashLen ='1' dashGap ='3' /><category showLabel='0' label='01/02/2018' /><category showLabel='0' label='02/02/2018' /></categories><dataset seriesName='' ><set value='18.9212' toolText=' 02/01/2007 18.9212' /><set value='18.0048' toolText=' 05/01/2007 18.0048' /><set value='20.1914' toolText=' 15/01/2007 20.1914' /><set value='23.6097' toolText=' 26/02/2007 23.6097' /><set value='21.2771' toolText=' 05/03/2007 21.2771' /><set value='23.5304' toolText=' 23/03/2007 23.5304' /><set value='23.6294' toolText=' 26/03/2007 23.6294' /><set value='23.9466' toolText=' 28/03/2007 23.9466' /><set value='26.4446' toolText=' 16/04/2007 26.4446' /><set value='30.1382' toolText=' 30/05/2007 30.1382' /><set value='31.5192' toolText=' 05/06/2007 31.5192' /><set value='30.6536' toolText=' 12/06/2007 30.6536' /><set value='31.4136' toolText=' 13/06/2007 31.4136' /><set value='31.4596' toolText=' 20/06/2007 31.4596' /><set value='35.8802' toolText=' 13/07/2007 35.8802' /><set value='35.3521' toolText=' 17/07/2007 35.3521' /><set value='28.8071' toolText=' 28/08/2007 28.8071' /><set value='31.8998' toolText=' 31/08/2007 31.8998' /><set value='32.7181' toolText=' 03/09/2007 32.7181' /><set value='29.6984' toolText=' 17/09/2007 29.6984' /><set value='36.3165' toolText=' 09/10/2007 36.3165' /><set value='38.0126' toolText=' 30/10/2007 38.0126' /><set value='40.8396' toolText=' 01/11/2007 40.8396' /><set value='30.1574' toolText=' 21/11/2007 30.1574' /><set value='31.4344' toolText=' 22/11/2007 31.4344' /><set value='33.0174' toolText=' 12/12/2007 33.0174' /><set value='31.7403' toolText=' 13/12/2007 31.7403' /><set value='25.5545' toolText=' 21/01/2008 25.5545' /><set value='26.9413' toolText=' 25/01/2008 26.9413' /><set value='27.0557' toolText=' 08/02/2008 27.0557' /><set value='26.571' toolText=' 11/02/2008 26.571' /><set value='30.9391' toolText=' 05/03/2008 30.9391' /><set value='31.3632' toolText=' 19/03/2008 31.3632' /><set value='32.2985' toolText=' 31/03/2008 32.2985' /><set value='33.6176' toolText=' 02/04/2008 33.6176' /><set value='32.7157' toolText=' 30/04/2008 32.7157' /><set value='33.0457' toolText=' 02/05/2008 33.0457' /><set value='34.4926' toolText=' 06/05/2008 34.4926' /><set value='38.7662' toolText=' 22/05/2008 38.7662' /><set value='34.5933' toolText=' 28/05/2008 34.5933' /><set value='29.613' toolText=' 18/07/2008 29.613' /><set value='30.6901' toolText=' 21/07/2008 30.6901' /><set value='32.32' toolText=' 22/07/2008 32.32' /><set value='33.5116' toolText=' 23/07/2008 33.5116' /><set value='32.2996' toolText=' 30/07/2008 32.2996' /><set value='26.5738' toolText=' 04/09/2008 26.5738' /><set value='20.6436' toolText=' 17/09/2008 20.6436' /><set value='14.3252' toolText=' 10/10/2008 14.3252' /><set value='16.3337' toolText=' 13/10/2008 16.3337' /><set value='16.8852' toolText=' 14/10/2008 16.8852' /><set value='13.2019' toolText=' 17/10/2008 13.2019' /><set value='13.0723' toolText=' 12/11/2008 13.0723' /><set value='10.0086' toolText=' 21/11/2008 10.0086' /><set value='12.5345' toolText=' 30/12/2008 12.5345' /><set value='13.4129' toolText=' 02/01/2009 13.4129' /><set value='14.2707' toolText=' 06/01/2009 14.2707' /><set value='12.9431' toolText=' 14/01/2009 12.9431' /><set value='16.6825' toolText=' 09/02/2009 16.6825' /><set value='17.8017' toolText=' 19/03/2009 17.8017' /><set value='16.2109' toolText=' 20/03/2009 16.2109' /><set value='16.4783' toolText=' 23/03/2009 16.4783' /><set value='16.3305' toolText=' 30/03/2009 16.3305' /><set value='20.0189' toolText=' 07/05/2009 20.0189' /><set value='23.2709' toolText=' 03/06/2009 23.2709' /><set value='21.9618' toolText=' 08/06/2009 21.9618' /><set value='22.3557' toolText=' 10/06/2009 22.3557' /><set value='22.8484' toolText=' 11/06/2009 22.8484' /><set value='21.4054' toolText=' 22/06/2009 21.4054' /><set value='24.3985' toolText=' 20/07/2009 24.3985' /><set value='24.9868' toolText=' 31/07/2009 24.9868' /><set value='27.6706' toolText=' 14/08/2009 27.6706' /><set value='27.3907' toolText=' 28/08/2009 27.3907' /><set value='27.1898' toolText=' 31/08/2009 27.1898' /><set value='28.9623' toolText=' 04/09/2009 28.9623' /><set value='29.0843' toolText=' 17/09/2009 29.0843' /><set value='24.5779' toolText=' 02/10/2009 24.5779' /><set value='27.319' toolText=' 09/10/2009 27.319' /><set value='25.9411' toolText=' 19/11/2009 25.9411' /><set value='25.9699' toolText=' 20/11/2009 25.9699' /><set value='30.4979' toolText=' 08/01/2010 30.4979' /><set value='30.6523' toolText=' 11/01/2010 30.6523' /><set value='31.0133' toolText=' 14/01/2010 31.0133' /><set value='30.1387' toolText=' 02/02/2010 30.1387' /><set value='28.1306' toolText=' 08/02/2010 28.1306' /><set value='28.5169' toolText=' 09/02/2010 28.5169' /><set value='30.995' toolText=' 19/02/2010 30.995' /><set value='34.8873' toolText=' 06/04/2010 34.8873' /><set value='34.9856' toolText=' 14/04/2010 34.9856' /><set value='33.2692' toolText=' 22/04/2010 33.2692' /><set value='33.4294' toolText=' 30/04/2010 33.4294' /><set value='33.1854' toolText=' 03/05/2010 33.1854' /><set value='29.7598' toolText=' 17/05/2010 29.7598' /><set value='26.4616' toolText=' 25/05/2010 26.4616' /><set value='28.9397' toolText=' 28/05/2010 28.9397' /><set value='26.917' toolText=' 01/07/2010 26.917' /><set value='28.3532' toolText=' 20/07/2010 28.3532' /><set value='28.939' toolText=' 21/07/2010 28.939' /><set value='29.6248' toolText=' 23/08/2010 29.6248' /><set value='28.1897' toolText=' 25/08/2010 28.1897' /><set value='28.9982' toolText=' 30/09/2010 28.9982' /><set value='32.6317' toolText=' 06/10/2010 32.6317' /><set value='32.5651' toolText=' 08/10/2010 32.5651' /><set value='31.994' toolText=' 11/10/2010 31.994' /><set value='32.2648' toolText=' 15/10/2010 32.2648' /><set value='30.7001' toolText=' 16/11/2010 30.7001' /><set value='34.7379' toolText=' 14/12/2010 34.7379' /><set value='34.5486' toolText=' 15/12/2010 34.5486' /><set value='35.6721' toolText=' 29/12/2010 35.6721' /><set value='35.3088' toolText=' 30/12/2010 35.3088' /><set value='35.5535' toolText=' 05/01/2011 35.5535' /><set value='32.9648' toolText=' 03/02/2011 32.9648' /><set value='32.6866' toolText=' 09/03/2011 32.6866' /><set value='29.8792' toolText=' 16/03/2011 29.8792' /><set value='30.7034' toolText=' 18/03/2011 30.7034' /><set value='31.0871' toolText=' 21/03/2011 31.0871' /><set value='32.4983' toolText=' 01/04/2011 32.4983' /><set value='32.4043' toolText=' 06/04/2011 32.4043' /><set value='28.073' toolText=' 07/06/2011 28.073' /><set value='28.3741' toolText=' 08/06/2011 28.3741' /><set value='28.3363' toolText=' 09/06/2011 28.3363' /><set value='27.5687' toolText=' 10/06/2011 27.5687' /><set value='28.4155' toolText=' 14/06/2011 28.4155' /><set value='22.0911' toolText=' 18/07/2011 22.0911' /><set value='23.0876' toolText=' 19/07/2011 23.0876' /><set value='17.8852' toolText=' 19/08/2011 17.8852' /><set value='19.2242' toolText=' 29/08/2011 19.2242' /><set value='20.1017' toolText=' 30/08/2011 20.1017' /><set value='19.2396' toolText=' 05/09/2011 19.2396' /><set value='17.0194' toolText=' 04/10/2011 17.0194' /><set value='23.3455' toolText=' 28/10/2011 23.3455' /><set value='21.0867' toolText=' 11/11/2011 21.0867' /><set value='20.1594' toolText=' 18/11/2011 20.1594' /><set value='19.2936' toolText=' 21/11/2011 19.2936' /><set value='18.4546' toolText=' 24/11/2011 18.4546' /><set value='19.5937' toolText=' 19/12/2011 19.5937' /><set value='22.3137' toolText=' 23/01/2012 22.3137' /><set value='23.6446' toolText=' 06/02/2012 23.6446' /><set value='23.4987' toolText=' 07/02/2012 23.4987' /><set value='23.369' toolText=' 08/02/2012 23.369' /><set value='24.688' toolText=' 09/03/2012 24.688' /><set value='25.8692' toolText=' 16/03/2012 25.8692' /><set value='24.9361' toolText=' 22/03/2012 24.9361' /><set value='21.6168' toolText=' 23/04/2012 21.6168' /><set value='23.5186' toolText=' 27/04/2012 23.5186' /><set value='23.172' toolText=' 30/04/2012 23.172' /><set value='22.4005' toolText=' 04/05/2012 22.4005' /><set value='23.9279' toolText=' 22/05/2012 23.9279' /><set value='22.4712' toolText=' 01/06/2012 22.4712' /><set value='26.1031' toolText=' 12/07/2012 26.1031' /><set value='26.9875' toolText=' 18/07/2012 26.9875' /><set value='26.9833' toolText=' 19/07/2012 26.9833' /><set value='25.5401' toolText=' 25/07/2012 25.5401' /><set value='30.9715' toolText=' 08/08/2012 30.9715' /><set value='29.5724' toolText=' 14/09/2012 29.5724' /><set value='29.4719' toolText=' 24/09/2012 29.4719' /><set value='30.3644' toolText=' 05/10/2012 30.3644' /><set value='30.296' toolText=' 08/10/2012 30.296' /><set value='31.0156' toolText=' 22/10/2012 31.0156' /><set value='31.3573' toolText=' 24/10/2012 31.3573' /><set value='27.9804' toolText=' 13/11/2012 27.9804' /><set value='28.1292' toolText=' 04/12/2012 28.1292' /><set value='28.471' toolText=' 24/12/2012 28.471' /><set value='28.6156' toolText=' 27/12/2012 28.6156' /><set value='28.1935' toolText=' 28/12/2012 28.1935' /><set value='29.5442' toolText=' 03/01/2013 29.5442' /><set value='32.0067' toolText=' 22/02/2013 32.0067' /><set value='31.8512' toolText=' 27/02/2013 31.8512' /><set value='31.1998' toolText=' 15/03/2013 31.1998' /><set value='31.204' toolText=' 18/03/2013 31.204' /><set value='29.6644' toolText=' 05/04/2013 29.6644' /><set value='31.761' toolText=' 11/04/2013 31.761' /><set value='30.2419' toolText=' 24/04/2013 30.2419' /><set value='30.0658' toolText=' 29/04/2013 30.0658' /><set value='30.0574' toolText=' 06/06/2013 30.0574' /><set value='30.0534' toolText=' 07/06/2013 30.0534' /><set value='29.7381' toolText=' 17/06/2013 29.7381' /><set value='30.7903' toolText=' 30/07/2013 30.7903' /><set value='26.9383' toolText=' 06/08/2013 26.9383' /><set value='28.5094' toolText=' 12/08/2013 28.5094' /><set value='28.3923' toolText=' 26/08/2013 28.3923' /><set value='28.125' toolText=' 27/08/2013 28.125' /><set value='27.6152' toolText=' 30/08/2013 27.6152' /><set value='29.6999' toolText=' 20/09/2013 29.6999' /><set value='29.583' toolText=' 10/10/2013 29.583' /><set value='32.2317' toolText=' 06/11/2013 32.2317' /><set value='32.9503' toolText=' 15/11/2013 32.9503' /><set value='33.1215' toolText=' 18/11/2013 33.1215' /><set value='31.5549' toolText=' 16/12/2013 31.5549' /><set value='31.1913' toolText=' 18/12/2013 31.1913' /><set value='33.1298' toolText=' 30/12/2013 33.1298' /><set value='34.7591' toolText=' 16/01/2014 34.7591' /><set value='32.8143' toolText=' 04/02/2014 32.8143' /><set value='32.9035' toolText=' 05/02/2014 32.9035' /><set value='32.9586' toolText=' 03/03/2014 32.9586' /><set value='32.2878' toolText=' 14/03/2014 32.2878' /><set value='35.0944' toolText=' 15/04/2014 35.0944' /><set value='34.9375' toolText=' 17/04/2014 34.9375' /><set value='36.1389' toolText=' 25/04/2014 36.1389' /><set value='36.0881' toolText=' 28/04/2014 36.0881' /><set value='36.984' toolText=' 29/04/2014 36.984' /><set value='38.2408' toolText=' 05/05/2014 38.2408' /><set value='39.3406' toolText=' 23/06/2014 39.3406' /><set value='38.1687' toolText=' 26/06/2014 38.1687' /><set value='37.8216' toolText=' 16/07/2014 37.8216' /><set value='38.0246' toolText=' 17/07/2014 38.0246' /><set value='38.2533' toolText=' 23/07/2014 38.2533' /><set value='33.1073' toolText=' 07/08/2014 33.1073' /><set value='37.5669' toolText=' 05/09/2014 37.5669' /><set value='34.0657' toolText=' 02/10/2014 34.0657' /><set value='34.45' toolText=' 03/10/2014 34.45' /><set value='34.3767' toolText=' 06/10/2014 34.3767' /><set value='32.5462' toolText=' 16/10/2014 32.5462' /><set value='33.604' toolText=' 17/10/2014 33.604' /><set value='35.5594' toolText=' 21/11/2014 35.5594' /><set value='29.2651' toolText=' 15/12/2014 29.2651' /><set value='31.8685' toolText=' 24/12/2014 31.8685' /><set value='31.7951' toolText=' 29/12/2014 31.7951' /><set value='31.6266' toolText=' 02/01/2015 31.6266' /><set value='29.0986' toolText=' 20/01/2015 29.0986' /><set value='30.3749' toolText=' 27/01/2015 30.3749' /><set value='34.1508' toolText=' 12/03/2015 34.1508' /><set value='33.8383' toolText=' 16/03/2015 33.8383' /><set value='33.79' toolText=' 17/03/2015 33.79' /><set value='35.4314' toolText=' 07/04/2015 35.4314' /><set value='35.2114' toolText=' 08/04/2015 35.2114' /><set value='36.6725' toolText=' 20/04/2015 36.6725' /><set value='41.6632' toolText=' 02/06/2015 41.6632' /><set value='40.3693' toolText=' 05/06/2015 40.3693' /><set value='40.3736' toolText=' 08/06/2015 40.3736' /><set value='40.3472' toolText=' 09/06/2015 40.3472' /><set value='41.1701' toolText=' 02/07/2015 41.1701' /><set value='42.1651' toolText=' 03/08/2015 42.1651' /><set value='34.7148' toolText=' 24/08/2015 34.7148' /><set value='36.6255' toolText=' 25/08/2015 36.6255' /><set value='37.0058' toolText=' 26/08/2015 37.0058' /><set value='39.0284' toolText=' 28/08/2015 39.0284' /><set value='34.7909' toolText=' 28/09/2015 34.7909' /><set value='36.7507' toolText=' 09/10/2015 36.7507' /><set value='37.5786' toolText=' 04/11/2015 37.5786' /><set value='33.2025' toolText=' 13/11/2015 33.2025' /><set value='32.4417' toolText=' 16/11/2015 32.4417' /><set value='33.1128' toolText=' 25/11/2015 33.1128' /><set value='33.9272' toolText=' 30/11/2015 33.9272' /><set value='31.5736' toolText=' 29/12/2015 31.5736' /><set value='26.1955' toolText=' 20/01/2016 26.1955' /><set value='26.7669' toolText=' 03/02/2016 26.7669' /><set value='27.3521' toolText=' 04/02/2016 27.3521' /><set value='27.8321' toolText=' 05/02/2016 27.8321' /><set value='25.6149' toolText=' 10/02/2016 25.6149' /><set value='26.4423' toolText=' 15/02/2016 26.4423' /><set value='19.8866' toolText=' 17/02/2016 19.8866' /><set value='27.2744' toolText=' 22/04/2016 27.2744' /><set value='26.7486' toolText=' 25/04/2016 26.7486' /><set value='27.8275' toolText=' 26/04/2016 27.8275' /><set value='26.3599' toolText=' 12/05/2016 26.3599' /><set value='26.5748' toolText=' 17/05/2016 26.5748' /><set value='22.5244' toolText=' 27/06/2016 22.5244' /><set value='25.9442' toolText=' 14/07/2016 25.9442' /><set value='26.0052' toolText=' 15/07/2016 26.0052' /><set value='25.3945' toolText=' 26/07/2016 25.3945' /><set value='31.2852' toolText=' 18/08/2016 31.2852' /><set value='30.6605' toolText=' 22/08/2016 30.6605' /><set value='32.5958' toolText=' 30/09/2016 32.5958' /><set value='32.4125' toolText=' 03/10/2016 32.4125' /><set value='32.7179' toolText=' 04/10/2016 32.7179' /><set value='33.2627' toolText=' 12/10/2016 33.2627' /><set value='33.5353' toolText=' 14/10/2016 33.5353' /><set value='30.1625' toolText=' 11/11/2016 30.1625' /><set value='36.2833' toolText=' 22/12/2016 36.2833' /><set value='36.1189' toolText=' 23/12/2016 36.1189' /><set value='36.443' toolText=' 27/12/2016 36.443' /><set value='36.6497' toolText=' 28/12/2016 36.6497' /><set value='35.87' toolText=' 26/01/2017 35.87' /><set value='33.857' toolText=' 27/02/2017 33.857' /><set value='34.6985' toolText=' 06/03/2017 34.6985' /><set value='34.9567' toolText=' 14/03/2017 34.9567' /><set value='35.191' toolText=' 15/03/2017 35.191' /><set value='35.2054' toolText=' 21/03/2017 35.2054' /><set value='36.5777' toolText=' 12/04/2017 36.5777' /><set value='34.9041' toolText=' 02/05/2017 34.9041' /><set value='35.3631' toolText=' 08/05/2017 35.3631' /><set value='32.3891' toolText=' 02/06/2017 32.3891' /><set value='32.5326' toolText=' 05/06/2017 32.5326' /><set value='32.3843' toolText=' 30/06/2017 32.3843' /><set value='34.5002' toolText=' 14/07/2017 34.5002' /><set value='27.7213' toolText=' 15/08/2017 27.7213' /><set value='27.5943' toolText=' 17/08/2017 27.5943' /><set value='27.7506' toolText=' 23/08/2017 27.7506' /><set value='27.6627' toolText=' 24/08/2017 27.6627' /><set value='28.5125' toolText=' 01/09/2017 28.5125' /><set value='28.0534' toolText=' 06/09/2017 28.0534' /><set value='26.2268' toolText=' 26/09/2017 26.2268' /><set value='24.9179' toolText=' 12/10/2017 24.9179' /><set value='22.7592' toolText=' 10/11/2017 22.7592' /><set value='22.2024' toolText=' 13/11/2017 22.2024' /><set value='25.8068' toolText=' 22/12/2017 25.8068' /><set value='26.5' toolText=' 19/01/2018 26.5' /><set value='27.61' toolText=' 30/01/2018 27.61' /><set value='28.02' toolText=' 01/02/2018 28.02' /><set value='27.3' toolText=' 02/02/2018 27.3' /></dataset><styles>

      <definition>
         <!-- <style name='CanvasAnim' type='animation' param='_yScale' start='0' duration='1' Easing='Bounce'/> -->
		 <!-- <style name='myAnim' type='animation'   param='_alpha' start='0' duration='1' />-->
		 <style name='myValuesFont' type='font' size='16'  bold='1' isHTML='1'/>
		 <style name='myTrendValuesFont' type='font' isHTML='1'/>
		 <style name='MyFirstShadow' type='Shadow'  Color= '999999' distance='3'  Alpha= '50' angle='90' blurY='3' blurX='3' />
		 <style name='lineas' type='ANIMATION' duration='1' start='0' param='_alpha' />
		 <style name='myToolTipFont' type='font' font='Arial' size='10' color='4E4E4E'/>
		 <style name='myToolTipFont' type='font' font='Arial' size='12' color='616161'/>
		 <style name='myLegendFont' type='font' size='12' color='808080' bold='1' />
		
      </definition>

      <application>
		 <apply toObject='DataValues' styles='myValuesFont' />
		 <apply toObject='DataPlot' styles='MyFirstShadow' />
		 <apply toObject='DivLines' styles='lineas' />
		 <apply toObject='ToolTip' styles='myToolTipFont' />
		 <apply toObject='Legend' styles='myLegendFont' />
		 <apply toObject='TrendValues' styles='myTrendValuesFont' />
      </application>   

   </styles></chart>