<chart labelDisplay='none'
	bgColor='FFF1E0'
	bgAlpha= '100'
	showBorder= '0'
	BorderColor = 'd7cec5'
	BorderAlpha = '100'
	adjustDiv='0'
	showYAxisValues='1'
	setAdaptiveYMin='1'
	showValues='0' 
	decimals='2' 
	formatNumberScale='0' 
	decimalSeparator=',' 
	thousandSeparator='.' 
	connectNullData='1'
	paletteColors='386ab0,834946,8f781c,d89839,852662' 
	drawAnchors='1' 
	anchorRadius='1'
	anchorBgAlpha ='0' 
	lineThickness ='3'
	animation='1'
	showLabels='1'
	showPlotBorder='0'
	canvasPlotThickness='1'
	canvasBgColor ='FFF1E0'
	canvasBgAngle ='90'
	canvasBorderThickness='1'
	canvasBorderColor='C6C6C6'
	PlotBorderColor='ffffff'
	plotGradientColor='000000'
	plotFillAngle = '90'
	plotFillRatio='99'
	plotFillAlpha='100,80'
	useRoundEdges='0'
	showAlternateHGridColor='0'
	alternateVGridAlpha='50'
	alternateVGridColor='A4A4A4'
	divLineIsColor='4C4C4C'
	divLineThickness='1'
	divLineIsDashed='1' divLineDashLen='1' divLineDashGap='3'
	vDivLineIsDashed='0'
	vDivLineColor ='d6d6d6'
	baseFont='Arial'
	baseFontColor='4C4C4C' 
	outCnvBaseFontSize='10'
	legendBorderThickness ='0'
	legendBorderColor = 'ffffff'
	legendShadow ='0'
	chartLeftMargin='0'
	chartRightMargin='1'
	chartTopMargin='8'
	chartBottomMargin='0'
	showShadow='0'
	><categories><category showLabel='0' label='04/01/1999' /><category showLabel='0' label='13/01/1999' /><vLine color='edebeb' thickness='1' dashed ='0' dashLen ='1' dashGap ='3' /><category showLabel='0' label='05/03/1999' /><category showLabel='0' label='11/03/1999' /><category showLabel='0' label='29/03/1999' /><vLine color='edebeb' thickness='1' dashed ='0' dashLen ='1' dashGap ='3' /><category showLabel='0' label='21/05/1999' /><category showLabel='0' label='24/05/1999' /><vLine color='edebeb' thickness='1' dashed ='0' dashLen ='1' dashGap ='3' /><category showLabel='0' label='14/06/1999' /><vLine color='edebeb' thickness='1' dashed ='0' dashLen ='1' dashGap ='3' /><category showLabel='0' label='19/07/1999' /><vLine color='edebeb' thickness='1' dashed ='0' dashLen ='1' dashGap ='3' /><category showLabel='0' label='03/08/1999' /><category showLabel='0' label='06/08/1999' /><vLine color='edebeb' thickness='1' dashed ='0' dashLen ='1' dashGap ='3' /><category showLabel='0' label='08/10/1999' /><category showLabel='0' label='11/10/1999' /><category showLabel='0' label='21/10/1999' /><vLine color='edebeb' thickness='1' dashed ='0' dashLen ='1' dashGap ='3' /><category showLabel='0' label='20/12/1999' /><vLine color='c6c6c6' thickness='1' dashed ='0' dashLen ='1' dashGap ='3' /><category showLabel='1' label='2000' /><vLine color='edebeb' thickness='1' dashed ='0' dashLen ='1' dashGap ='3' /><category showLabel='0' label='11/02/2000' /><category showLabel='0' label='25/02/2000' /><category showLabel='0' label='28/02/2000' /><vLine color='edebeb' thickness='1' dashed ='0' dashLen ='1' dashGap ='3' /><category showLabel='0' label='06/03/2000' /><vLine color='edebeb' thickness='1' dashed ='0' dashLen ='1' dashGap ='3' /><category showLabel='0' label='24/05/2000' /><vLine color='edebeb' thickness='1' dashed ='0' dashLen ='1' dashGap ='3' /><category showLabel='0' label='14/06/2000' /><vLine color='edebeb' thickness='1' dashed ='0' dashLen ='1' dashGap ='3' /><category showLabel='0' label='04/07/2000' /><category showLabel='0' label='13/07/2000' /><category showLabel='0' label='14/07/2000' /><category showLabel='0' label='18/07/2000' /><vLine color='edebeb' thickness='1' dashed ='0' dashLen ='1' dashGap ='3' /><category showLabel='0' label='16/08/2000' /><vLine color='edebeb' thickness='1' dashed ='0' dashLen ='1' dashGap ='3' /><category showLabel='0' label='27/10/2000' /><vLine color='edebeb' thickness='1' dashed ='0' dashLen ='1' dashGap ='3' /><category showLabel='0' label='28/11/2000' /><category showLabel='0' label='29/11/2000' /><category showLabel='0' label='30/11/2000' /><vLine color='c6c6c6' thickness='1' dashed ='0' dashLen ='1' dashGap ='3' /><category showLabel='1' label='2001' /><vLine color='edebeb' thickness='1' dashed ='0' dashLen ='1' dashGap ='3' /><category showLabel='0' label='05/02/2001' /><vLine color='edebeb' thickness='1' dashed ='0' dashLen ='1' dashGap ='3' /><category showLabel='0' label='22/03/2001' /><vLine color='edebeb' thickness='1' dashed ='0' dashLen ='1' dashGap ='3' /><category showLabel='0' label='11/04/2001' /><category showLabel='0' label='17/04/2001' /><category showLabel='0' label='18/04/2001' /><category showLabel='0' label='19/04/2001' /><category showLabel='0' label='24/04/2001' /><vLine color='edebeb' thickness='1' dashed ='0' dashLen ='1' dashGap ='3' /><category showLabel='0' label='03/05/2001' /><category showLabel='0' label='25/05/2001' /><vLine color='edebeb' thickness='1' dashed ='0' dashLen ='1' dashGap ='3' /><category showLabel='0' label='03/09/2001' /><category showLabel='0' label='04/09/2001' /><category showLabel='0' label='14/09/2001' /><vLine color='edebeb' thickness='1' dashed ='0' dashLen ='1' dashGap ='3' /><category showLabel='0' label='31/10/2001' /><vLine color='edebeb' thickness='1' dashed ='0' dashLen ='1' dashGap ='3' /><category showLabel='0' label='19/11/2001' /><vLine color='c6c6c6' thickness='1' dashed ='0' dashLen ='1' dashGap ='3' /><category showLabel='1' label='2002' /><category showLabel='0' label='18/01/2002' /><category showLabel='0' label='21/01/2002' /><category showLabel='0' label='24/01/2002' /><vLine color='edebeb' thickness='1' dashed ='0' dashLen ='1' dashGap ='3' /><category showLabel='0' label='04/03/2002' /><vLine color='edebeb' thickness='1' dashed ='0' dashLen ='1' dashGap ='3' /><category showLabel='0' label='30/05/2002' /><category showLabel='0' label='31/05/2002' /><vLine color='edebeb' thickness='1' dashed ='0' dashLen ='1' dashGap ='3' /><category showLabel='0' label='07/06/2002' /><category showLabel='0' label='10/06/2002' /><category showLabel='0' label='11/06/2002' /><vLine color='edebeb' thickness='1' dashed ='0' dashLen ='1' dashGap ='3' /><category showLabel='0' label='01/08/2002' /><vLine color='edebeb' thickness='1' dashed ='0' dashLen ='1' dashGap ='3' /><category showLabel='0' label='01/10/2002' /><category showLabel='0' label='14/10/2002' /><category showLabel='0' label='25/10/2002' /><category showLabel='0' label='28/10/2002' /><vLine color='edebeb' thickness='1' dashed ='0' dashLen ='1' dashGap ='3' /><category showLabel='0' label='25/11/2002' /><vLine color='edebeb' thickness='1' dashed ='0' dashLen ='1' dashGap ='3' /><category showLabel='0' label='02/12/2002' /><vLine color='c6c6c6' thickness='1' dashed ='0' dashLen ='1' dashGap ='3' /><category showLabel='1' label='2003' /><vLine color='edebeb' thickness='1' dashed ='0' dashLen ='1' dashGap ='3' /><category showLabel='0' label='12/03/2003' /><category showLabel='0' label='13/03/2003' /><category showLabel='0' label='14/03/2003' /><category showLabel='0' label='31/03/2003' /><vLine color='edebeb' thickness='1' dashed ='0' dashLen ='1' dashGap ='3' /><category showLabel='0' label='15/04/2003' /><vLine color='edebeb' thickness='1' dashed ='0' dashLen ='1' dashGap ='3' /><category showLabel='0' label='20/06/2003' /><vLine color='edebeb' thickness='1' dashed ='0' dashLen ='1' dashGap ='3' /><category showLabel='0' label='01/07/2003' /><category showLabel='0' label='31/07/2003' /><vLine color='edebeb' thickness='1' dashed ='0' dashLen ='1' dashGap ='3' /><category showLabel='0' label='01/08/2003' /><vLine color='edebeb' thickness='1' dashed ='0' dashLen ='1' dashGap ='3' /><category showLabel='0' label='04/09/2003' /><category showLabel='0' label='30/09/2003' /><vLine color='edebeb' thickness='1' dashed ='0' dashLen ='1' dashGap ='3' /><category showLabel='0' label='10/10/2003' /><vLine color='edebeb' thickness='1' dashed ='0' dashLen ='1' dashGap ='3' /><category showLabel='0' label='16/12/2003' /><category showLabel='0' label='17/12/2003' /><category showLabel='0' label='18/12/2003' /><category showLabel='0' label='22/12/2003' /><vLine color='c6c6c6' thickness='1' dashed ='0' dashLen ='1' dashGap ='3' /><category showLabel='1' label='2004' /><vLine color='edebeb' thickness='1' dashed ='0' dashLen ='1' dashGap ='3' /><category showLabel='0' label='24/03/2004' /><vLine color='edebeb' thickness='1' dashed ='0' dashLen ='1' dashGap ='3' /><category showLabel='0' label='26/04/2004' /><vLine color='edebeb' thickness='1' dashed ='0' dashLen ='1' dashGap ='3' /><category showLabel='0' label='04/05/2004' /><category showLabel='0' label='05/05/2004' /><vLine color='edebeb' thickness='1' dashed ='0' dashLen ='1' dashGap ='3' /><category showLabel='0' label='20/07/2004' /><vLine color='edebeb' thickness='1' dashed ='0' dashLen ='1' dashGap ='3' /><category showLabel='0' label='05/08/2004' /><category showLabel='0' label='10/08/2004' /><category showLabel='0' label='13/08/2004' /><vLine color='edebeb' thickness='1' dashed ='0' dashLen ='1' dashGap ='3' /><category showLabel='0' label='20/09/2004' /><category showLabel='0' label='21/09/2004' /><category showLabel='0' label='27/09/2004' /><vLine color='edebeb' thickness='1' dashed ='0' dashLen ='1' dashGap ='3' /><category showLabel='0' label='28/10/2004' /><vLine color='edebeb' thickness='1' dashed ='0' dashLen ='1' dashGap ='3' /><category showLabel='0' label='08/11/2004' /><vLine color='c6c6c6' thickness='1' dashed ='0' dashLen ='1' dashGap ='3' /><category showLabel='1' label='2005' /><vLine color='edebeb' thickness='1' dashed ='0' dashLen ='1' dashGap ='3' /><category showLabel='0' label='04/02/2005' /><category showLabel='0' label='07/02/2005' /><category showLabel='0' label='15/02/2005' /><vLine color='edebeb' thickness='1' dashed ='0' dashLen ='1' dashGap ='3' /><category showLabel='0' label='01/03/2005' /><vLine color='edebeb' thickness='1' dashed ='0' dashLen ='1' dashGap ='3' /><category showLabel='0' label='28/04/2005' /><vLine color='edebeb' thickness='1' dashed ='0' dashLen ='1' dashGap ='3' /><category showLabel='0' label='23/05/2005' /><vLine color='edebeb' thickness='1' dashed ='0' dashLen ='1' dashGap ='3' /><category showLabel='0' label='24/06/2005' /><category showLabel='0' label='27/06/2005' /><vLine color='edebeb' thickness='1' dashed ='0' dashLen ='1' dashGap ='3' /><category showLabel='0' label='07/10/2005' /><category showLabel='0' label='11/10/2005' /><category showLabel='0' label='24/10/2005' /><vLine color='edebeb' thickness='1' dashed ='0' dashLen ='1' dashGap ='3' /><category showLabel='0' label='04/11/2005' /><category showLabel='0' label='11/11/2005' /><category showLabel='0' label='14/11/2005' /><vLine color='edebeb' thickness='1' dashed ='0' dashLen ='1' dashGap ='3' /><category showLabel='0' label='07/12/2005' /><vLine color='c6c6c6' thickness='1' dashed ='0' dashLen ='1' dashGap ='3' /><category showLabel='1' label='2006' /><category showLabel='0' label='30/01/2006' /><vLine color='edebeb' thickness='1' dashed ='0' dashLen ='1' dashGap ='3' /><category showLabel='0' label='13/03/2006' /><category showLabel='0' label='31/03/2006' /><vLine color='edebeb' thickness='1' dashed ='0' dashLen ='1' dashGap ='3' /><category showLabel='0' label='03/04/2006' /><vLine color='edebeb' thickness='1' dashed ='0' dashLen ='1' dashGap ='3' /><category showLabel='0' label='03/05/2006' /><category showLabel='0' label='16/05/2006' /><category showLabel='0' label='22/05/2006' /><vLine color='edebeb' thickness='1' dashed ='0' dashLen ='1' dashGap ='3' /><category showLabel='0' label='04/08/2006' /><category showLabel='0' label='17/08/2006' /><category showLabel='0' label='18/08/2006' /><category showLabel='0' label='31/08/2006' /><vLine color='edebeb' thickness='1' dashed ='0' dashLen ='1' dashGap ='3' /><category showLabel='0' label='18/09/2006' /><vLine color='edebeb' thickness='1' dashed ='0' dashLen ='1' dashGap ='3' /><category showLabel='0' label='28/11/2006' /><vLine color='edebeb' thickness='1' dashed ='0' dashLen ='1' dashGap ='3' /><category showLabel='0' label='14/12/2006' /><vLine color='c6c6c6' thickness='1' dashed ='0' dashLen ='1' dashGap ='3' /><category showLabel='1' label='2007' /><category showLabel='0' label='04/01/2007' /><category showLabel='0' label='10/01/2007' /><vLine color='edebeb' thickness='1' dashed ='0' dashLen ='1' dashGap ='3' /><category showLabel='0' label='09/02/2007' /><category showLabel='0' label='19/02/2007' /><vLine color='edebeb' thickness='1' dashed ='0' dashLen ='1' dashGap ='3' /><category showLabel='0' label='14/03/2007' /><vLine color='edebeb' thickness='1' dashed ='0' dashLen ='1' dashGap ='3' /><category showLabel='0' label='22/05/2007' /><category showLabel='0' label='23/05/2007' /><vLine color='edebeb' thickness='1' dashed ='0' dashLen ='1' dashGap ='3' /><category showLabel='0' label='12/06/2007' /><vLine color='edebeb' thickness='1' dashed ='0' dashLen ='1' dashGap ='3' /><category showLabel='0' label='20/07/2007' /><vLine color='edebeb' thickness='1' dashed ='0' dashLen ='1' dashGap ='3' /><category showLabel='0' label='15/08/2007' /><vLine color='edebeb' thickness='1' dashed ='0' dashLen ='1' dashGap ='3' /><category showLabel='0' label='26/09/2007' /><vLine color='edebeb' thickness='1' dashed ='0' dashLen ='1' dashGap ='3' /><category showLabel='0' label='08/10/2007' /><category showLabel='0' label='09/10/2007' /><category showLabel='0' label='12/10/2007' /><vLine color='edebeb' thickness='1' dashed ='0' dashLen ='1' dashGap ='3' /><category showLabel='0' label='30/11/2007' /><vLine color='edebeb' thickness='1' dashed ='0' dashLen ='1' dashGap ='3' /><category showLabel='0' label='04/12/2007' /><vLine color='c6c6c6' thickness='1' dashed ='0' dashLen ='1' dashGap ='3' /><category showLabel='1' label='2008' /><category showLabel='0' label='22/02/2008' /><category showLabel='0' label='25/02/2008' /><vLine color='edebeb' thickness='1' dashed ='0' dashLen ='1' dashGap ='3' /><category showLabel='0' label='07/04/2008' /><vLine color='edebeb' thickness='1' dashed ='0' dashLen ='1' dashGap ='3' /><category showLabel='0' label='14/05/2008' /><vLine color='edebeb' thickness='1' dashed ='0' dashLen ='1' dashGap ='3' /><category showLabel='0' label='27/06/2008' /><vLine color='edebeb' thickness='1' dashed ='0' dashLen ='1' dashGap ='3' /><category showLabel='0' label='09/07/2008' /><category showLabel='0' label='11/07/2008' /><category showLabel='0' label='14/07/2008' /><vLine color='edebeb' thickness='1' dashed ='0' dashLen ='1' dashGap ='3' /><category showLabel='0' label='19/09/2008' /><vLine color='edebeb' thickness='1' dashed ='0' dashLen ='1' dashGap ='3' /><category showLabel='0' label='07/10/2008' /><category showLabel='0' label='28/10/2008' /><vLine color='edebeb' thickness='1' dashed ='0' dashLen ='1' dashGap ='3' /><category showLabel='0' label='14/11/2008' /><category showLabel='0' label='28/11/2008' /><vLine color='edebeb' thickness='1' dashed ='0' dashLen ='1' dashGap ='3' /><category showLabel='0' label='01/12/2008' /><vLine color='c6c6c6' thickness='1' dashed ='0' dashLen ='1' dashGap ='3' /><category showLabel='1' label='2009' /><category showLabel='0' label='23/01/2009' /><vLine color='edebeb' thickness='1' dashed ='0' dashLen ='1' dashGap ='3' /><category showLabel='0' label='20/02/2009' /><vLine color='edebeb' thickness='1' dashed ='0' dashLen ='1' dashGap ='3' /><category showLabel='0' label='20/03/2009' /><vLine color='edebeb' thickness='1' dashed ='0' dashLen ='1' dashGap ='3' /><category showLabel='0' label='17/04/2009' /><category showLabel='0' label='20/04/2009' /><category showLabel='0' label='30/04/2009' /><vLine color='edebeb' thickness='1' dashed ='0' dashLen ='1' dashGap ='3' /><category showLabel='0' label='12/06/2009' /><vLine color='edebeb' thickness='1' dashed ='0' dashLen ='1' dashGap ='3' /><category showLabel='0' label='30/07/2009' /><vLine color='edebeb' thickness='1' dashed ='0' dashLen ='1' dashGap ='3' /><category showLabel='0' label='18/08/2009' /><vLine color='edebeb' thickness='1' dashed ='0' dashLen ='1' dashGap ='3' /><category showLabel='0' label='03/09/2009' /><category showLabel='0' label='04/09/2009' /><vLine color='edebeb' thickness='1' dashed ='0' dashLen ='1' dashGap ='3' /><category showLabel='0' label='16/10/2009' /><category showLabel='0' label='20/10/2009' /><category showLabel='0' label='26/10/2009' /><vLine color='c6c6c6' thickness='1' dashed ='0' dashLen ='1' dashGap ='3' /><category showLabel='1' label='2010' /><category showLabel='0' label='20/01/2010' /><category showLabel='0' label='21/01/2010' /><category showLabel='0' label='28/01/2010' /><vLine color='edebeb' thickness='1' dashed ='0' dashLen ='1' dashGap ='3' /><category showLabel='0' label='15/03/2010' /><vLine color='edebeb' thickness='1' dashed ='0' dashLen ='1' dashGap ='3' /><category showLabel='0' label='07/05/2010' /><category showLabel='0' label='18/05/2010' /><vLine color='edebeb' thickness='1' dashed ='0' dashLen ='1' dashGap ='3' /><category showLabel='0' label='08/06/2010' /><category showLabel='0' label='09/06/2010' /><vLine color='edebeb' thickness='1' dashed ='0' dashLen ='1' dashGap ='3' /><category showLabel='0' label='12/07/2010' /><vLine color='edebeb' thickness='1' dashed ='0' dashLen ='1' dashGap ='3' /><category showLabel='0' label='23/08/2010' /><vLine color='edebeb' thickness='1' dashed ='0' dashLen ='1' dashGap ='3' /><category showLabel='0' label='24/09/2010' /><vLine color='edebeb' thickness='1' dashed ='0' dashLen ='1' dashGap ='3' /><category showLabel='0' label='18/10/2010' /><category showLabel='0' label='26/10/2010' /><category showLabel='0' label='27/10/2010' /><vLine color='edebeb' thickness='1' dashed ='0' dashLen ='1' dashGap ='3' /><category showLabel='0' label='02/11/2010' /><category showLabel='0' label='30/11/2010' /><vLine color='c6c6c6' thickness='1' dashed ='0' dashLen ='1' dashGap ='3' /><category showLabel='1' label='2011' /><category showLabel='0' label='17/01/2011' /><vLine color='edebeb' thickness='1' dashed ='0' dashLen ='1' dashGap ='3' /><category showLabel='0' label='14/03/2011' /><category showLabel='0' label='15/03/2011' /><category showLabel='0' label='29/03/2011' /><vLine color='edebeb' thickness='1' dashed ='0' dashLen ='1' dashGap ='3' /><category showLabel='0' label='08/04/2011' /><vLine color='edebeb' thickness='1' dashed ='0' dashLen ='1' dashGap ='3' /><category showLabel='0' label='23/05/2011' /><vLine color='edebeb' thickness='1' dashed ='0' dashLen ='1' dashGap ='3' /><category showLabel='0' label='18/07/2011' /><category showLabel='0' label='29/07/2011' /><vLine color='edebeb' thickness='1' dashed ='0' dashLen ='1' dashGap ='3' /><category showLabel='0' label='01/08/2011' /><vLine color='edebeb' thickness='1' dashed ='0' dashLen ='1' dashGap ='3' /><category showLabel='0' label='12/09/2011' /><vLine color='edebeb' thickness='1' dashed ='0' dashLen ='1' dashGap ='3' /><category showLabel='0' label='14/10/2011' /><category showLabel='0' label='27/10/2011' /><vLine color='edebeb' thickness='1' dashed ='0' dashLen ='1' dashGap ='3' /><category showLabel='0' label='09/12/2011' /><category showLabel='0' label='16/12/2011' /><category showLabel='0' label='19/12/2011' /><vLine color='c6c6c6' thickness='1' dashed ='0' dashLen ='1' dashGap ='3' /><category showLabel='1' label='2012' /><category showLabel='0' label='12/01/2012' /><vLine color='edebeb' thickness='1' dashed ='0' dashLen ='1' dashGap ='3' /><category showLabel='0' label='10/04/2012' /><vLine color='edebeb' thickness='1' dashed ='0' dashLen ='1' dashGap ='3' /><category showLabel='0' label='02/05/2012' /><category showLabel='0' label='04/05/2012' /><category showLabel='0' label='07/05/2012' /><vLine color='edebeb' thickness='1' dashed ='0' dashLen ='1' dashGap ='3' /><category showLabel='0' label='14/06/2012' /><vLine color='edebeb' thickness='1' dashed ='0' dashLen ='1' dashGap ='3' /><category showLabel='0' label='24/07/2012' /><vLine color='edebeb' thickness='1' dashed ='0' dashLen ='1' dashGap ='3' /><category showLabel='0' label='13/09/2012' /><category showLabel='0' label='14/09/2012' /><category showLabel='0' label='20/09/2012' /><category showLabel='0' label='21/09/2012' /><vLine color='edebeb' thickness='1' dashed ='0' dashLen ='1' dashGap ='3' /><category showLabel='0' label='26/10/2012' /><vLine color='edebeb' thickness='1' dashed ='0' dashLen ='1' dashGap ='3' /><category showLabel='0' label='29/11/2012' /><vLine color='edebeb' thickness='1' dashed ='0' dashLen ='1' dashGap ='3' /><category showLabel='0' label='10/12/2012' /><vLine color='c6c6c6' thickness='1' dashed ='0' dashLen ='1' dashGap ='3' /><category showLabel='1' label='2013' /><vLine color='edebeb' thickness='1' dashed ='0' dashLen ='1' dashGap ='3' /><category showLabel='0' label='06/02/2013' /><category showLabel='0' label='07/02/2013' /><category showLabel='0' label='21/02/2013' /><vLine color='edebeb' thickness='1' dashed ='0' dashLen ='1' dashGap ='3' /><category showLabel='0' label='12/03/2013' /><category showLabel='0' label='14/03/2013' /><vLine color='edebeb' thickness='1' dashed ='0' dashLen ='1' dashGap ='3' /><category showLabel='0' label='21/05/2013' /><vLine color='edebeb' thickness='1' dashed ='0' dashLen ='1' dashGap ='3' /><category showLabel='0' label='26/06/2013' /><category showLabel='0' label='27/06/2013' /><vLine color='edebeb' thickness='1' dashed ='0' dashLen ='1' dashGap ='3' /><category showLabel='0' label='03/07/2013' /><vLine color='edebeb' thickness='1' dashed ='0' dashLen ='1' dashGap ='3' /><category showLabel='0' label='16/09/2013' /><vLine color='edebeb' thickness='1' dashed ='0' dashLen ='1' dashGap ='3' /><category showLabel='0' label='03/10/2013' /><category showLabel='0' label='21/10/2013' /><vLine color='edebeb' thickness='1' dashed ='0' dashLen ='1' dashGap ='3' /><category showLabel='0' label='12/11/2013' /><category showLabel='0' label='13/11/2013' /><category showLabel='0' label='20/11/2013' /><vLine color='c6c6c6' thickness='1' dashed ='0' dashLen ='1' dashGap ='3' /><category showLabel='1' label='2014' /><vLine color='edebeb' thickness='1' dashed ='0' dashLen ='1' dashGap ='3' /><category showLabel='0' label='03/03/2014' /><category showLabel='0' label='06/03/2014' /><category showLabel='0' label='31/03/2014' /><vLine color='edebeb' thickness='1' dashed ='0' dashLen ='1' dashGap ='3' /><category showLabel='0' label='01/04/2014' /><category showLabel='0' label='11/04/2014' /><vLine color='edebeb' thickness='1' dashed ='0' dashLen ='1' dashGap ='3' /><category showLabel='0' label='20/06/2014' /><vLine color='edebeb' thickness='1' dashed ='0' dashLen ='1' dashGap ='3' /><category showLabel='0' label='16/07/2014' /><category showLabel='0' label='28/07/2014' /><vLine color='edebeb' thickness='1' dashed ='0' dashLen ='1' dashGap ='3' /><category showLabel='0' label='15/08/2014' /><category showLabel='0' label='18/08/2014' /><vLine color='edebeb' thickness='1' dashed ='0' dashLen ='1' dashGap ='3' /><category showLabel='0' label='10/10/2014' /><category showLabel='0' label='16/10/2014' /><vLine color='edebeb' thickness='1' dashed ='0' dashLen ='1' dashGap ='3' /><category showLabel='0' label='25/11/2014' /><vLine color='edebeb' thickness='1' dashed ='0' dashLen ='1' dashGap ='3' /><category showLabel='0' label='05/12/2014' /><vLine color='c6c6c6' thickness='1' dashed ='0' dashLen ='1' dashGap ='3' /><category showLabel='1' label='2015' /><category showLabel='0' label='05/01/2015' /><category showLabel='0' label='09/01/2015' /><vLine color='edebeb' thickness='1' dashed ='0' dashLen ='1' dashGap ='3' /><category showLabel='0' label='17/02/2015' /><vLine color='edebeb' thickness='1' dashed ='0' dashLen ='1' dashGap ='3' /><category showLabel='0' label='08/04/2015' /><vLine color='edebeb' thickness='1' dashed ='0' dashLen ='1' dashGap ='3' /><category showLabel='0' label='11/05/2015' /><category showLabel='0' label='22/05/2015' /><category showLabel='0' label='25/05/2015' /><vLine color='edebeb' thickness='1' dashed ='0' dashLen ='1' dashGap ='3' /><category showLabel='0' label='05/08/2015' /><category showLabel='0' label='24/08/2015' /><vLine color='edebeb' thickness='1' dashed ='0' dashLen ='1' dashGap ='3' /><category showLabel='0' label='14/09/2015' /><vLine color='edebeb' thickness='1' dashed ='0' dashLen ='1' dashGap ='3' /><category showLabel='0' label='02/10/2015' /><category showLabel='0' label='09/10/2015' /><category showLabel='0' label='12/10/2015' /><vLine color='edebeb' thickness='1' dashed ='0' dashLen ='1' dashGap ='3' /><category showLabel='0' label='17/11/2015' /><vLine color='edebeb' thickness='1' dashed ='0' dashLen ='1' dashGap ='3' /><category showLabel='0' label='14/12/2015' /><vLine color='c6c6c6' thickness='1' dashed ='0' dashLen ='1' dashGap ='3' /><category showLabel='1' label='2016' /><category showLabel='0' label='22/02/2016' /><category showLabel='0' label='25/02/2016' /><category showLabel='0' label='26/02/2016' /><vLine color='edebeb' thickness='1' dashed ='0' dashLen ='1' dashGap ='3' /><category showLabel='0' label='11/03/2016' /><vLine color='edebeb' thickness='1' dashed ='0' dashLen ='1' dashGap ='3' /><category showLabel='0' label='07/04/2016' /><vLine color='edebeb' thickness='1' dashed ='0' dashLen ='1' dashGap ='3' /><category showLabel='0' label='10/05/2016' /><vLine color='edebeb' thickness='1' dashed ='0' dashLen ='1' dashGap ='3' /><category showLabel='0' label='27/06/2016' /><vLine color='edebeb' thickness='1' dashed ='0' dashLen ='1' dashGap ='3' /><category showLabel='0' label='13/07/2016' /><category showLabel='0' label='14/07/2016' /><vLine color='edebeb' thickness='1' dashed ='0' dashLen ='1' dashGap ='3' /><category showLabel='0' label='10/08/2016' /><vLine color='edebeb' thickness='1' dashed ='0' dashLen ='1' dashGap ='3' /><category showLabel='0' label='08/09/2016' /><vLine color='edebeb' thickness='1' dashed ='0' dashLen ='1' dashGap ='3' /><category showLabel='0' label='31/10/2016' /><vLine color='edebeb' thickness='1' dashed ='0' dashLen ='1' dashGap ='3' /><category showLabel='0' label='28/11/2016' /><category showLabel='0' label='29/11/2016' /><category showLabel='0' label='30/11/2016' /><vLine color='edebeb' thickness='1' dashed ='0' dashLen ='1' dashGap ='3' /><category showLabel='0' label='02/12/2016' /><vLine color='c6c6c6' thickness='1' dashed ='0' dashLen ='1' dashGap ='3' /><category showLabel='1' label='2017' /><category showLabel='0' label='17/01/2017' /><vLine color='edebeb' thickness='1' dashed ='0' dashLen ='1' dashGap ='3' /><category showLabel='0' label='17/03/2017' /><vLine color='edebeb' thickness='1' dashed ='0' dashLen ='1' dashGap ='3' /><category showLabel='0' label='13/04/2017' /><category showLabel='0' label='18/04/2017' /><category showLabel='0' label='25/04/2017' /><vLine color='edebeb' thickness='1' dashed ='0' dashLen ='1' dashGap ='3' /><category showLabel='0' label='30/06/2017' /><vLine color='edebeb' thickness='1' dashed ='0' dashLen ='1' dashGap ='3' /><category showLabel='0' label='21/08/2017' /><category showLabel='0' label='29/08/2017' /><vLine color='edebeb' thickness='1' dashed ='0' dashLen ='1' dashGap ='3' /><category showLabel='0' label='01/09/2017' /><category showLabel='0' label='04/09/2017' /><category showLabel='0' label='14/09/2017' /><category showLabel='0' label='27/09/2017' /><vLine color='edebeb' thickness='1' dashed ='0' dashLen ='1' dashGap ='3' /><category showLabel='0' label='10/10/2017' /><vLine color='edebeb' thickness='1' dashed ='0' dashLen ='1' dashGap ='3' /><category showLabel='0' label='29/12/2017' /><vLine color='c6c6c6' thickness='1' dashed ='0' dashLen ='1' dashGap ='3' /><category showLabel='1' label='2018' /></categories><dataset seriesName='' ><set value='5.6494' toolText=' 04/01/1999 5.6494' /><set value='5.1354' toolText=' 13/01/1999 5.1354' /><set value='5.8931' toolText=' 05/03/1999 5.8931' /><set value='5.8976' toolText=' 11/03/1999 5.8976' /><set value='5.5102' toolText=' 29/03/1999 5.5102' /><set value='6.5989' toolText=' 21/05/1999 6.5989' /><set value='6.4856' toolText=' 24/05/1999 6.4856' /><set value='6.3854' toolText=' 14/06/1999 6.3854' /><set value='6.7602' toolText=' 19/07/1999 6.7602' /><set value='6.2287' toolText=' 03/08/1999 6.2287' /><set value='5.7888' toolText=' 06/08/1999 5.7888' /><set value='6.4509' toolText=' 08/10/1999 6.4509' /><set value='6.5293' toolText=' 11/10/1999 6.5293' /><set value='5.9716' toolText=' 21/10/1999 5.9716' /><set value='10.1707' toolText=' 20/12/1999 10.1707' /><set value='10.1225' toolText=' 25/01/2000 10.1225' /><set value='13.2632' toolText=' 11/02/2000 13.2632' /><set value='12.3618' toolText=' 25/02/2000 12.3618' /><set value='12.1873' toolText=' 28/02/2000 12.1873' /><set value='13.5288' toolText=' 06/03/2000 13.5288' /><set value='8.3675' toolText=' 24/05/2000 8.3675' /><set value='9.5912' toolText=' 14/06/2000 9.5912' /><set value='10.1009' toolText=' 04/07/2000 10.1009' /><set value='10.419' toolText=' 13/07/2000 10.419' /><set value='10.5844' toolText=' 14/07/2000 10.5844' /><set value='10.0923' toolText=' 18/07/2000 10.0923' /><set value='10.4798' toolText=' 16/08/2000 10.4798' /><set value='9.6392' toolText=' 27/10/2000 9.6392' /><set value='7.5528' toolText=' 28/11/2000 7.5528' /><set value='7.7269' toolText=' 29/11/2000 7.7269' /><set value='7.4918' toolText=' 30/11/2000 7.4918' /><set value='8.7594' toolText=' 24/01/2001 8.7594' /><set value='8.1885' toolText=' 05/02/2001 8.1885' /><set value='6.6207' toolText=' 22/03/2001 6.6207' /><set value='8.1017' toolText=' 11/04/2001 8.1017' /><set value='7.8884' toolText=' 17/04/2001 7.8884' /><set value='8.241' toolText=' 18/04/2001 8.241' /><set value='8.3456' toolText=' 19/04/2001 8.3456' /><set value='7.6659' toolText=' 24/04/2001 7.6659' /><set value='7.6575' toolText=' 03/05/2001 7.6575' /><set value='7.3437' toolText=' 25/05/2001 7.3437' /><set value='5.0831' toolText=' 03/09/2001 5.0831' /><set value='5.2748' toolText=' 04/09/2001 5.2748' /><set value='4.1989' toolText=' 14/09/2001 4.1989' /><set value='5.5361' toolText=' 31/10/2001 5.5361' /><set value='6.7255' toolText=' 19/11/2001 6.7255' /><set value='5.6147' toolText=' 16/01/2002 5.6147' /><set value='5.8454' toolText=' 18/01/2002 5.8454' /><set value='5.7495' toolText=' 21/01/2002 5.7495' /><set value='6.1023' toolText=' 24/01/2002 6.1023' /><set value='5.8281' toolText=' 04/03/2002 5.8281' /><set value='4.5386' toolText=' 30/05/2002 4.5386' /><set value='4.7042' toolText=' 31/05/2002 4.7042' /><set value='4.0898' toolText=' 07/06/2002 4.0898' /><set value='4.0988' toolText=' 10/06/2002 4.0988' /><set value='4.1945' toolText=' 11/06/2002 4.1945' /><set value='3.6763' toolText=' 01/08/2002 3.6763' /><set value='3.0926' toolText=' 01/10/2002 3.0926' /><set value='3.4018' toolText=' 14/10/2002 3.4018' /><set value='3.8593' toolText=' 25/10/2002 3.8593' /><set value='3.9418' toolText=' 28/10/2002 3.9418' /><set value='4.2206' toolText=' 25/11/2002 4.2206' /><set value='4.2817' toolText=' 02/12/2002 4.2817' /><set value='3.6457' toolText=' 26/02/2003 3.6457' /><set value='3.3755' toolText=' 12/03/2003 3.3755' /><set value='3.576' toolText=' 13/03/2003 3.576' /><set value='3.7372' toolText=' 14/03/2003 3.7372' /><set value='3.7025' toolText=' 31/03/2003 3.7025' /><set value='4.2902' toolText=' 15/04/2003 4.2902' /><set value='4.4909' toolText=' 20/06/2003 4.4909' /><set value='4.2902' toolText=' 01/07/2003 4.2902' /><set value='4.4865' toolText=' 31/07/2003 4.4865' /><set value='4.4341' toolText=' 01/08/2003 4.4341' /><set value='4.7826' toolText=' 04/09/2003 4.7826' /><set value='4.3776' toolText=' 30/09/2003 4.3776' /><set value='4.6563' toolText=' 10/10/2003 4.6563' /><set value='5.0352' toolText=' 16/12/2003 5.0352' /><set value='5.0003' toolText=' 17/12/2003 5.0003' /><set value='5.0615' toolText=' 18/12/2003 5.0615' /><set value='5.0483' toolText=' 22/12/2003 5.0483' /><set value='5.8544' toolText=' 19/02/2004 5.8544' /><set value='5.2182' toolText=' 24/03/2004 5.2182' /><set value='5.5797' toolText=' 26/04/2004 5.5797' /><set value='5.4229' toolText=' 04/05/2004 5.4229' /><set value='5.4969' toolText=' 05/05/2004 5.4969' /><set value='5.2813' toolText=' 20/07/2004 5.2813' /><set value='5.2104' toolText=' 05/08/2004 5.2104' /><set value='5.011' toolText=' 10/08/2004 5.011' /><set value='4.9622' toolText=' 13/08/2004 4.9622' /><set value='5.3564' toolText=' 20/09/2004 5.3564' /><set value='5.3612' toolText=' 21/09/2004 5.3612' /><set value='5.2591' toolText=' 27/09/2004 5.2591' /><set value='5.7863' toolText=' 28/10/2004 5.7863' /><set value='5.9281' toolText=' 08/11/2004 5.9281' /><set value='6.3122' toolText=' 04/01/2005 6.3122' /><set value='6.3706' toolText=' 04/02/2005 6.3706' /><set value='6.4382' toolText=' 07/02/2005 6.4382' /><set value='6.5506' toolText=' 15/02/2005 6.5506' /><set value='6.3122' toolText=' 01/03/2005 6.3122' /><set value='5.8578' toolText=' 28/04/2005 5.8578' /><set value='6.2945' toolText=' 23/05/2005 6.2945' /><set value='6.3709' toolText=' 24/06/2005 6.3709' /><set value='6.3136' toolText=' 27/06/2005 6.3136' /><set value='6.6565' toolText=' 07/10/2005 6.6565' /><set value='6.7185' toolText=' 11/10/2005 6.7185' /><set value='6.5995' toolText=' 24/10/2005 6.5995' /><set value='6.0662' toolText=' 04/11/2005 6.0662' /><set value='6.1581' toolText=' 11/11/2005 6.1581' /><set value='6.1824' toolText=' 14/11/2005 6.1824' /><set value='6.1288' toolText=' 07/12/2005 6.1288' /><set value='5.9441' toolText=' 24/01/2006 5.9441' /><set value='6.0997' toolText=' 30/01/2006 6.0997' /><set value='6.5519' toolText=' 13/03/2006 6.5519' /><set value='6.2991' toolText=' 31/03/2006 6.2991' /><set value='6.3135' toolText=' 03/04/2006 6.3135' /><set value='6.1581' toolText=' 03/05/2006 6.1581' /><set value='6.2005' toolText=' 16/05/2006 6.2005' /><set value='5.9129' toolText=' 22/05/2006 5.9129' /><set value='6.6421' toolText=' 04/08/2006 6.6421' /><set value='6.5822' toolText=' 17/08/2006 6.5822' /><set value='6.5723' toolText=' 18/08/2006 6.5723' /><set value='6.6469' toolText=' 31/08/2006 6.6469' /><set value='6.4486' toolText=' 18/09/2006 6.4486' /><set value='7.7025' toolText=' 28/11/2006 7.7025' /><set value='8.294' toolText=' 14/12/2006 8.294' /><set value='8.3295' toolText=' 03/01/2007 8.3295' /><set value='8.4356' toolText=' 04/01/2007 8.4356' /><set value='8.3496' toolText=' 10/01/2007 8.3496' /><set value='8.6683' toolText=' 09/02/2007 8.6683' /><set value='8.7087' toolText=' 19/02/2007 8.7087' /><set value='7.687' toolText=' 14/03/2007 7.687' /><set value='8.5792' toolText=' 22/05/2007 8.5792' /><set value='8.7129' toolText=' 23/05/2007 8.7129' /><set value='8.3216' toolText=' 12/06/2007 8.3216' /><set value='8.8469' toolText=' 20/07/2007 8.8469' /><set value='9.1765' toolText=' 15/08/2007 9.1765' /><set value='10.1084' toolText=' 26/09/2007 10.1084' /><set value='9.8974' toolText=' 08/10/2007 9.8974' /><set value='9.8871' toolText=' 09/10/2007 9.8871' /><set value='11.092' toolText=' 12/10/2007 11.092' /><set value='11.9789' toolText=' 30/11/2007 11.9789' /><set value='12.136' toolText=' 04/12/2007 12.136' /><set value='9.83' toolText=' 20/02/2008 9.83' /><set value='9.9346' toolText=' 22/02/2008 9.9346' /><set value='10.0812' toolText=' 25/02/2008 10.0812' /><set value='10.2172' toolText=' 07/04/2008 10.2172' /><set value='10.3148' toolText=' 14/05/2008 10.3148' /><set value='8.9478' toolText=' 27/06/2008 8.9478' /><set value='9.4713' toolText=' 09/07/2008 9.4713' /><set value='9.1349' toolText=' 11/07/2008 9.1349' /><set value='9.1669' toolText=' 14/07/2008 9.1669' /><set value='9.5834' toolText=' 19/09/2008 9.5834' /><set value='8.8999' toolText=' 07/10/2008 8.8999' /><set value='6.7965' toolText=' 28/10/2008 6.7965' /><set value='8.3369' toolText=' 14/11/2008 8.3369' /><set value='8.7676' toolText=' 28/11/2008 8.7676' /><set value='8.5633' toolText=' 01/12/2008 8.5633' /><set value='9.0659' toolText=' 05/01/2009 9.0659' /><set value='8.0995' toolText=' 23/01/2009 8.0995' /><set value='7.5586' toolText=' 20/02/2009 7.5586' /><set value='8.1714' toolText=' 20/03/2009 8.1714' /><set value='8.5797' toolText=' 17/04/2009 8.5797' /><set value='8.3921' toolText=' 20/04/2009 8.3921' /><set value='7.9561' toolText=' 30/04/2009 7.9561' /><set value='8.8468' toolText=' 12/06/2009 8.8468' /><set value='10.1889' toolText=' 30/07/2009 10.1889' /><set value='9.555' toolText=' 18/08/2009 9.555' /><set value='9.8263' toolText=' 03/09/2009 9.8263' /><set value='9.9263' toolText=' 04/09/2009 9.9263' /><set value='10.7459' toolText=' 16/10/2009 10.7459' /><set value='10.8202' toolText=' 20/10/2009 10.8202' /><set value='10.7972' toolText=' 26/10/2009 10.7972' /><set value='11.6169' toolText=' 04/01/2010 11.6169' /><set value='10.6968' toolText=' 20/01/2010 10.6968' /><set value='10.6147' toolText=' 21/01/2010 10.6147' /><set value='10.1254' toolText=' 28/01/2010 10.1254' /><set value='10.3656' toolText=' 15/03/2010 10.3656' /><set value='9.0027' toolText=' 07/05/2010 9.0027' /><set value='9.5241' toolText=' 18/05/2010 9.5241' /><set value='9.1616' toolText=' 08/06/2010 9.1616' /><set value='9.18' toolText=' 09/06/2010 9.18' /><set value='9.8407' toolText=' 12/07/2010 9.8407' /><set value='10.5291' toolText=' 23/08/2010 10.5291' /><set value='11.2145' toolText=' 24/09/2010 11.2145' /><set value='11.8601' toolText=' 18/10/2010 11.8601' /><set value='11.7109' toolText=' 26/10/2010 11.7109' /><set value='11.6469' toolText=' 27/10/2010 11.6469' /><set value='11.9363' toolText=' 02/11/2010 11.9363' /><set value='10.3328' toolText=' 30/11/2010 10.3328' /><set value='10.7743' toolText=' 04/01/2011 10.7743' /><set value='11.0705' toolText=' 17/01/2011 11.0705' /><set value='11.0548' toolText=' 14/03/2011 11.0548' /><set value='10.8719' toolText=' 15/03/2011 10.8719' /><set value='11.2186' toolText=' 29/03/2011 11.2186' /><set value='11.493' toolText=' 08/04/2011 11.493' /><set value='10.9052' toolText=' 23/05/2011 10.9052' /><set value='10.1352' toolText=' 18/07/2011 10.1352' /><set value='10.234' toolText=' 29/07/2011 10.234' /><set value='10.053' toolText=' 01/08/2011 10.053' /><set value='8.3515' toolText=' 12/09/2011 8.3515' /><set value='10.0662' toolText=' 14/10/2011 10.0662' /><set value='10.4185' toolText=' 27/10/2011 10.4185' /><set value='9.6431' toolText=' 09/12/2011 9.6431' /><set value='8.9042' toolText=' 16/12/2011 8.9042' /><set value='8.9459' toolText=' 19/12/2011 8.9459' /><set value='9.5113' toolText=' 03/01/2012 9.5113' /><set value='9.2962' toolText=' 12/01/2012 9.2962' /><set value='8.0128' toolText=' 10/04/2012 8.0128' /><set value='7.3988' toolText=' 02/05/2012 7.3988' /><set value='7.5306' toolText=' 04/05/2012 7.5306' /><set value='7.7319' toolText=' 07/05/2012 7.7319' /><set value='7.4621' toolText=' 14/06/2012 7.4621' /><set value='6.4852' toolText=' 24/07/2012 6.4852' /><set value='8.5068' toolText=' 13/09/2012 8.5068' /><set value='8.7021' toolText=' 14/09/2012 8.7021' /><set value='8.4053' toolText=' 20/09/2012 8.4053' /><set value='8.5294' toolText=' 21/09/2012 8.5294' /><set value='7.6651' toolText=' 26/10/2012 7.6651' /><set value='7.605' toolText=' 29/11/2012 7.605' /><set value='7.4621' toolText=' 10/12/2012 7.4621' /><set value='8.1647' toolText=' 18/01/2013 8.1647' /><set value='7.5861' toolText=' 06/02/2013 7.5861' /><set value='7.5334' toolText=' 07/02/2013 7.5334' /><set value='7.1331' toolText=' 21/02/2013 7.1331' /><set value='8.3001' toolText=' 12/03/2013 8.3001' /><set value='8.642' toolText=' 14/03/2013 8.642' /><set value='8.2662' toolText=' 21/05/2013 8.2662' /><set value='7.4749' toolText=' 26/06/2013 7.4749' /><set value='7.484' toolText=' 27/06/2013 7.484' /><set value='7.3029' toolText=' 03/07/2013 7.3029' /><set value='8.4992' toolText=' 16/09/2013 8.4992' /><set value='8.8674' toolText=' 03/10/2013 8.8674' /><set value='9.8482' toolText=' 21/10/2013 9.8482' /><set value='9.4838' toolText=' 12/11/2013 9.4838' /><set value='9.4876' toolText=' 13/11/2013 9.4876' /><set value='9.3409' toolText=' 20/11/2013 9.3409' /><set value='9.6692' toolText=' 20/01/2014 9.6692' /><set value='8.3943' toolText=' 03/03/2014 8.3943' /><set value='8.8001' toolText=' 06/03/2014 8.8001' /><set value='8.8735' toolText=' 31/03/2014 8.8735' /><set value='8.8966' toolText=' 01/04/2014 8.8966' /><set value='8.8695' toolText=' 11/04/2014 8.8695' /><set value='10.262' toolText=' 20/06/2014 10.262' /><set value='9.8069' toolText=' 16/07/2014 9.8069' /><set value='9.7748' toolText=' 28/07/2014 9.7748' /><set value='9.3596' toolText=' 15/08/2014 9.3596' /><set value='9.4355' toolText=' 18/08/2014 9.4355' /><set value='9.3438' toolText=' 10/10/2014 9.3438' /><set value='8.7567' toolText=' 16/10/2014 8.7567' /><set value='10.4336' toolText=' 25/11/2014 10.4336' /><set value='10.9795' toolText=' 05/12/2014 10.9795' /><set value='9.7601' toolText=' 02/01/2015 9.7601' /><set value='9.4317' toolText=' 05/01/2015 9.4317' /><set value='9.3249' toolText=' 09/01/2015 9.3249' /><set value='10.7867' toolText=' 17/02/2015 10.7867' /><set value='10.8879' toolText=' 08/04/2015 10.8879' /><set value='11.5065' toolText=' 11/05/2015 11.5065' /><set value='11.3016' toolText=' 22/05/2015 11.3016' /><set value='11.1863' toolText=' 25/05/2015 11.1863' /><set value='12.1524' toolText=' 05/08/2015 12.1524' /><set value='10.3823' toolText=' 24/08/2015 10.3823' /><set value='9.7751' toolText=' 14/09/2015 9.7751' /><set value='9.0653' toolText=' 02/10/2015 9.0653' /><set value='9.8819' toolText=' 09/10/2015 9.8819' /><set value='9.9034' toolText=' 12/10/2015 9.9034' /><set value='10.6004' toolText=' 17/11/2015 10.6004' /><set value='9.0119' toolText=' 14/12/2015 9.0119' /><set value='7.4664' toolText=' 11/02/2016 7.4664' /><set value='8.3835' toolText=' 22/02/2016 8.3835' /><set value='8.2937' toolText=' 25/02/2016 8.2937' /><set value='8.0305' toolText=' 26/02/2016 8.0305' /><set value='8.9547' toolText=' 11/03/2016 8.9547' /><set value='8.0148' toolText=' 07/04/2016 8.0148' /><set value='8.2374' toolText=' 10/05/2016 8.2374' /><set value='7.0351' toolText=' 27/06/2016 7.0351' /><set value='8.0121' toolText=' 13/07/2016 8.0121' /><set value='8.1076' toolText=' 14/07/2016 8.1076' /><set value='8.2655' toolText=' 10/08/2016 8.2655' /><set value='8.9534' toolText=' 08/09/2016 8.9534' /><set value='8.5034' toolText=' 31/10/2016 8.5034' /><set value='7.4904' toolText=' 28/11/2016 7.4904' /><set value='7.5612' toolText=' 29/11/2016 7.5612' /><set value='7.5163' toolText=' 30/11/2016 7.5163' /><set value='7.3707' toolText=' 02/12/2016 7.3707' /><set value='8.7951' toolText=' 10/01/2017 8.7951' /><set value='8.6974' toolText=' 17/01/2017 8.6974' /><set value='10.1467' toolText=' 17/03/2017 10.1467' /><set value='9.7973' toolText=' 13/04/2017 9.7973' /><set value='9.7159' toolText=' 18/04/2017 9.7159' /><set value='10.0653' toolText=' 25/04/2017 10.0653' /><set value='8.8276' toolText=' 30/06/2017 8.8276' /><set value='8.9155' toolText=' 21/08/2017 8.9155' /><set value='8.7661' toolText=' 29/08/2017 8.7661' /><set value='8.8452' toolText=' 01/09/2017 8.8452' /><set value='8.7446' toolText=' 04/09/2017 8.7446' /><set value='8.8735' toolText=' 14/09/2017 8.8735' /><set value='9.0298' toolText=' 27/09/2017 9.0298' /><set value='8.8032' toolText=' 10/10/2017 8.8032' /><set value='8.125' toolText=' 29/12/2017 8.125' /><set value='8.409' toolText=' 25/01/2018 8.409' /></dataset><styles>

      <definition>
         <!-- <style name='CanvasAnim' type='animation' param='_yScale' start='0' duration='1' Easing='Bounce'/> -->
		 <!-- <style name='myAnim' type='animation'   param='_alpha' start='0' duration='1' />-->
		 <style name='myValuesFont' type='font' size='16'  bold='1' isHTML='1'/>
		 <style name='myTrendValuesFont' type='font' isHTML='1'/>
		 <style name='MyFirstShadow' type='Shadow'  Color= '999999' distance='3'  Alpha= '50' angle='90' blurY='3' blurX='3' />
		 <style name='lineas' type='ANIMATION' duration='1' start='0' param='_alpha' />
		 <style name='myToolTipFont' type='font' font='Arial' size='10' color='4E4E4E'/>
		 <style name='myToolTipFont' type='font' font='Arial' size='12' color='616161'/>
		 <style name='myLegendFont' type='font' size='12' color='808080' bold='1' />
		
      </definition>

      <application>
		 <apply toObject='DataValues' styles='myValuesFont' />
		 <apply toObject='DataPlot' styles='MyFirstShadow' />
		 <apply toObject='DivLines' styles='lineas' />
		 <apply toObject='ToolTip' styles='myToolTipFont' />
		 <apply toObject='Legend' styles='myLegendFont' />
		 <apply toObject='TrendValues' styles='myTrendValuesFont' />
      </application>   

   </styles></chart>
