<chart labelDisplay='none'
	bgColor='FFF1E0'
	bgAlpha= '100'
	showBorder= '0'
	BorderColor = 'd7cec5'
	BorderAlpha = '100'
	adjustDiv='0'
	showYAxisValues='1'
	setAdaptiveYMin='1'
	showValues='0' 
	decimals='2' 
	formatNumberScale='0' 
	decimalSeparator=',' 
	thousandSeparator='.' 
	connectNullData='1'
	paletteColors='386ab0,834946,8f781c,d89839,852662' 
	drawAnchors='1' 
	anchorRadius='1'
	anchorBgAlpha ='0' 
	lineThickness ='3'
	animation='1'
	showLabels='1'
	showPlotBorder='0'
	canvasPlotThickness='1'
	canvasBgColor ='FFF1E0'
	canvasBgAngle ='90'
	canvasBorderThickness='1'
	canvasBorderColor='C6C6C6'
	PlotBorderColor='ffffff'
	plotGradientColor='000000'
	plotFillAngle = '90'
	plotFillRatio='99'
	plotFillAlpha='100,80'
	useRoundEdges='0'
	showAlternateHGridColor='0'
	alternateVGridAlpha='50'
	alternateVGridColor='A4A4A4'
	divLineIsColor='4C4C4C'
	divLineThickness='1'
	divLineIsDashed='1' divLineDashLen='1' divLineDashGap='3'
	vDivLineIsDashed='0'
	vDivLineColor ='d6d6d6'
	baseFont='Arial'
	baseFontColor='4C4C4C' 
	outCnvBaseFontSize='10'
	legendBorderThickness ='0'
	legendBorderColor = 'ffffff'
	legendShadow ='0'
	chartLeftMargin='0'
	chartRightMargin='1'
	chartTopMargin='8'
	chartBottomMargin='0'
	showShadow='0'
	><categories><category showLabel='0' label='02/01/2007' /><category showLabel='0' label='03/01/2007' /><category showLabel='0' label='12/01/2007' /><category showLabel='0' label='23/01/2007' /><vLine color='edebeb' thickness='1' dashed ='0' dashLen ='1' dashGap ='3' /><category showLabel='0' label='05/03/2007' /><category showLabel='0' label='23/03/2007' /><category showLabel='0' label='26/03/2007' /><category showLabel='0' label='28/03/2007' /><vLine color='edebeb' thickness='1' dashed ='0' dashLen ='1' dashGap ='3' /><category showLabel='0' label='09/05/2007' /><category showLabel='0' label='11/05/2007' /><vLine color='edebeb' thickness='1' dashed ='0' dashLen ='1' dashGap ='3' /><category showLabel='0' label='05/06/2007' /><category showLabel='0' label='13/06/2007' /><category showLabel='0' label='14/06/2007' /><category showLabel='0' label='15/06/2007' /><category showLabel='0' label='26/06/2007' /><vLine color='edebeb' thickness='1' dashed ='0' dashLen ='1' dashGap ='3' /><category showLabel='0' label='06/08/2007' /><category showLabel='0' label='16/08/2007' /><category showLabel='0' label='31/08/2007' /><vLine color='edebeb' thickness='1' dashed ='0' dashLen ='1' dashGap ='3' /><category showLabel='0' label='03/09/2007' /><category showLabel='0' label='06/09/2007' /><category showLabel='0' label='20/09/2007' /><category showLabel='0' label='28/09/2007' /><vLine color='edebeb' thickness='1' dashed ='0' dashLen ='1' dashGap ='3' /><category showLabel='0' label='31/10/2007' /><vLine color='edebeb' thickness='1' dashed ='0' dashLen ='1' dashGap ='3' /><category showLabel='0' label='22/11/2007' /><category showLabel='0' label='23/11/2007' /><vLine color='edebeb' thickness='1' dashed ='0' dashLen ='1' dashGap ='3' /><category showLabel='0' label='07/12/2007' /><category showLabel='0' label='18/12/2007' /><vLine color='c6c6c6' thickness='1' dashed ='0' dashLen ='1' dashGap ='3' /><category showLabel='1' label='2008' /><category showLabel='0' label='16/01/2008' /><vLine color='edebeb' thickness='1' dashed ='0' dashLen ='1' dashGap ='3' /><category showLabel='0' label='11/02/2008' /><category showLabel='0' label='12/02/2008' /><category showLabel='0' label='26/02/2008' /><vLine color='edebeb' thickness='1' dashed ='0' dashLen ='1' dashGap ='3' /><category showLabel='0' label='31/03/2008' /><vLine color='edebeb' thickness='1' dashed ='0' dashLen ='1' dashGap ='3' /><category showLabel='0' label='25/04/2008' /><category showLabel='0' label='29/04/2008' /><vLine color='edebeb' thickness='1' dashed ='0' dashLen ='1' dashGap ='3' /><category showLabel='0' label='02/05/2008' /><category showLabel='0' label='05/05/2008' /><vLine color='edebeb' thickness='1' dashed ='0' dashLen ='1' dashGap ='3' /><category showLabel='0' label='20/06/2008' /><category showLabel='0' label='24/06/2008' /><vLine color='edebeb' thickness='1' dashed ='0' dashLen ='1' dashGap ='3' /><category showLabel='0' label='02/07/2008' /><category showLabel='0' label='04/07/2008' /><category showLabel='0' label='23/07/2008' /><category showLabel='0' label='24/07/2008' /><vLine color='edebeb' thickness='1' dashed ='0' dashLen ='1' dashGap ='3' /><category showLabel='0' label='12/08/2008' /><category showLabel='0' label='21/08/2008' /><vLine color='edebeb' thickness='1' dashed ='0' dashLen ='1' dashGap ='3' /><category showLabel='0' label='02/09/2008' /><category showLabel='0' label='15/09/2008' /><vLine color='edebeb' thickness='1' dashed ='0' dashLen ='1' dashGap ='3' /><category showLabel='0' label='10/10/2008' /><category showLabel='0' label='13/10/2008' /><category showLabel='0' label='16/10/2008' /><category showLabel='0' label='23/10/2008' /><vLine color='edebeb' thickness='1' dashed ='0' dashLen ='1' dashGap ='3' /><category showLabel='0' label='19/11/2008' /><vLine color='edebeb' thickness='1' dashed ='0' dashLen ='1' dashGap ='3' /><category showLabel='0' label='10/12/2008' /><category showLabel='0' label='30/12/2008' /><vLine color='c6c6c6' thickness='1' dashed ='0' dashLen ='1' dashGap ='3' /><category showLabel='1' label='2009' /><category showLabel='0' label='06/01/2009' /><vLine color='edebeb' thickness='1' dashed ='0' dashLen ='1' dashGap ='3' /><category showLabel='0' label='03/02/2009' /><vLine color='edebeb' thickness='1' dashed ='0' dashLen ='1' dashGap ='3' /><category showLabel='0' label='03/03/2009' /><category showLabel='0' label='12/03/2009' /><category showLabel='0' label='23/03/2009' /><category showLabel='0' label='24/03/2009' /><category showLabel='0' label='30/03/2009' /><vLine color='edebeb' thickness='1' dashed ='0' dashLen ='1' dashGap ='3' /><category showLabel='0' label='15/04/2009' /><vLine color='edebeb' thickness='1' dashed ='0' dashLen ='1' dashGap ='3' /><category showLabel='0' label='12/05/2009' /><category showLabel='0' label='26/05/2009' /><vLine color='edebeb' thickness='1' dashed ='0' dashLen ='1' dashGap ='3' /><category showLabel='0' label='12/06/2009' /><category showLabel='0' label='15/06/2009' /><category showLabel='0' label='18/06/2009' /><vLine color='edebeb' thickness='1' dashed ='0' dashLen ='1' dashGap ='3' /><category showLabel='0' label='08/07/2009' /><vLine color='edebeb' thickness='1' dashed ='0' dashLen ='1' dashGap ='3' /><category showLabel='0' label='14/08/2009' /><category showLabel='0' label='18/08/2009' /><vLine color='edebeb' thickness='1' dashed ='0' dashLen ='1' dashGap ='3' /><category showLabel='0' label='02/09/2009' /><category showLabel='0' label='03/09/2009' /><category showLabel='0' label='17/09/2009' /><vLine color='edebeb' thickness='1' dashed ='0' dashLen ='1' dashGap ='3' /><category showLabel='0' label='08/10/2009' /><category showLabel='0' label='12/10/2009' /><vLine color='edebeb' thickness='1' dashed ='0' dashLen ='1' dashGap ='3' /><category showLabel='0' label='03/11/2009' /><category showLabel='0' label='20/11/2009' /><category showLabel='0' label='23/11/2009' /><category showLabel='0' label='26/11/2009' /><vLine color='edebeb' thickness='1' dashed ='0' dashLen ='1' dashGap ='3' /><category showLabel='0' label='08/12/2009' /><category showLabel='0' label='15/12/2009' /><vLine color='c6c6c6' thickness='1' dashed ='0' dashLen ='1' dashGap ='3' /><category showLabel='1' label='2010' /><category showLabel='0' label='11/02/2010' /><category showLabel='0' label='12/02/2010' /><category showLabel='0' label='25/02/2010' /><vLine color='edebeb' thickness='1' dashed ='0' dashLen ='1' dashGap ='3' /><category showLabel='0' label='08/03/2010' /><vLine color='edebeb' thickness='1' dashed ='0' dashLen ='1' dashGap ='3' /><category showLabel='0' label='09/04/2010' /><category showLabel='0' label='26/04/2010' /><vLine color='edebeb' thickness='1' dashed ='0' dashLen ='1' dashGap ='3' /><category showLabel='0' label='03/05/2010' /><category showLabel='0' label='04/05/2010' /><category showLabel='0' label='12/05/2010' /><vLine color='edebeb' thickness='1' dashed ='0' dashLen ='1' dashGap ='3' /><category showLabel='0' label='18/06/2010' /><category showLabel='0' label='23/06/2010' /><vLine color='edebeb' thickness='1' dashed ='0' dashLen ='1' dashGap ='3' /><category showLabel='0' label='01/07/2010' /><category showLabel='0' label='23/07/2010' /><category showLabel='0' label='26/07/2010' /><category showLabel='0' label='28/07/2010' /><category showLabel='0' label='30/07/2010' /><vLine color='edebeb' thickness='1' dashed ='0' dashLen ='1' dashGap ='3' /><category showLabel='0' label='25/08/2010' /><category showLabel='0' label='30/08/2010' /><vLine color='edebeb' thickness='1' dashed ='0' dashLen ='1' dashGap ='3' /><category showLabel='0' label='13/10/2010' /><category showLabel='0' label='14/10/2010' /><vLine color='edebeb' thickness='1' dashed ='0' dashLen ='1' dashGap ='3' /><category showLabel='0' label='12/11/2010' /><category showLabel='0' label='30/11/2010' /><vLine color='edebeb' thickness='1' dashed ='0' dashLen ='1' dashGap ='3' /><category showLabel='0' label='10/12/2010' /><category showLabel='0' label='29/12/2010' /><category showLabel='0' label='30/12/2010' /><vLine color='c6c6c6' thickness='1' dashed ='0' dashLen ='1' dashGap ='3' /><category showLabel='1' label='2011' /><category showLabel='0' label='10/01/2011' /><category showLabel='0' label='12/01/2011' /><vLine color='edebeb' thickness='1' dashed ='0' dashLen ='1' dashGap ='3' /><category showLabel='0' label='09/02/2011' /><category showLabel='0' label='25/02/2011' /><vLine color='edebeb' thickness='1' dashed ='0' dashLen ='1' dashGap ='3' /><category showLabel='0' label='24/03/2011' /><category showLabel='0' label='25/03/2011' /><category showLabel='0' label='29/03/2011' /><vLine color='edebeb' thickness='1' dashed ='0' dashLen ='1' dashGap ='3' /><category showLabel='0' label='08/04/2011' /><vLine color='edebeb' thickness='1' dashed ='0' dashLen ='1' dashGap ='3' /><category showLabel='0' label='02/05/2011' /><category showLabel='0' label='09/05/2011' /><vLine color='edebeb' thickness='1' dashed ='0' dashLen ='1' dashGap ='3' /><category showLabel='0' label='13/06/2011' /><category showLabel='0' label='14/06/2011' /><category showLabel='0' label='15/06/2011' /><vLine color='edebeb' thickness='1' dashed ='0' dashLen ='1' dashGap ='3' /><category showLabel='0' label='06/07/2011' /><category showLabel='0' label='29/07/2011' /><vLine color='edebeb' thickness='1' dashed ='0' dashLen ='1' dashGap ='3' /><category showLabel='0' label='26/08/2011' /><vLine color='edebeb' thickness='1' dashed ='0' dashLen ='1' dashGap ='3' /><category showLabel='0' label='02/09/2011' /><category showLabel='0' label='05/09/2011' /><category showLabel='0' label='22/09/2011' /><vLine color='edebeb' thickness='1' dashed ='0' dashLen ='1' dashGap ='3' /><category showLabel='0' label='04/10/2011' /><category showLabel='0' label='11/10/2011' /><category showLabel='0' label='27/10/2011' /><vLine color='edebeb' thickness='1' dashed ='0' dashLen ='1' dashGap ='3' /><category showLabel='0' label='22/11/2011' /><category showLabel='0' label='23/11/2011' /><category showLabel='0' label='24/11/2011' /><category showLabel='0' label='28/11/2011' /><vLine color='edebeb' thickness='1' dashed ='0' dashLen ='1' dashGap ='3' /><category showLabel='0' label='20/12/2011' /><vLine color='c6c6c6' thickness='1' dashed ='0' dashLen ='1' dashGap ='3' /><category showLabel='1' label='2012' /><category showLabel='0' label='10/02/2012' /><category showLabel='0' label='13/02/2012' /><category showLabel='0' label='15/02/2012' /><category showLabel='0' label='20/02/2012' /><vLine color='edebeb' thickness='1' dashed ='0' dashLen ='1' dashGap ='3' /><category showLabel='0' label='19/03/2012' /><vLine color='edebeb' thickness='1' dashed ='0' dashLen ='1' dashGap ='3' /><category showLabel='0' label='30/04/2012' /><vLine color='edebeb' thickness='1' dashed ='0' dashLen ='1' dashGap ='3' /><category showLabel='0' label='03/05/2012' /><category showLabel='0' label='04/05/2012' /><category showLabel='0' label='09/05/2012' /><category showLabel='0' label='14/05/2012' /><vLine color='edebeb' thickness='1' dashed ='0' dashLen ='1' dashGap ='3' /><category showLabel='0' label='13/06/2012' /><category showLabel='0' label='15/06/2012' /><vLine color='edebeb' thickness='1' dashed ='0' dashLen ='1' dashGap ='3' /><category showLabel='0' label='23/07/2012' /><category showLabel='0' label='24/07/2012' /><category showLabel='0' label='25/07/2012' /><vLine color='edebeb' thickness='1' dashed ='0' dashLen ='1' dashGap ='3' /><category showLabel='0' label='02/08/2012' /><category showLabel='0' label='13/08/2012' /><vLine color='edebeb' thickness='1' dashed ='0' dashLen ='1' dashGap ='3' /><category showLabel='0' label='21/09/2012' /><vLine color='edebeb' thickness='1' dashed ='0' dashLen ='1' dashGap ='3' /><category showLabel='0' label='12/10/2012' /><category showLabel='0' label='15/10/2012' /><category showLabel='0' label='25/10/2012' /><category showLabel='0' label='29/10/2012' /><vLine color='edebeb' thickness='1' dashed ='0' dashLen ='1' dashGap ='3' /><category showLabel='0' label='28/11/2012' /><vLine color='edebeb' thickness='1' dashed ='0' dashLen ='1' dashGap ='3' /><category showLabel='0' label='19/12/2012' /><category showLabel='0' label='31/12/2012' /><vLine color='c6c6c6' thickness='1' dashed ='0' dashLen ='1' dashGap ='3' /><category showLabel='1' label='2013' /><category showLabel='0' label='25/01/2013' /><category showLabel='0' label='30/01/2013' /><vLine color='edebeb' thickness='1' dashed ='0' dashLen ='1' dashGap ='3' /><category showLabel='0' label='07/02/2013' /><category showLabel='0' label='25/02/2013' /><vLine color='edebeb' thickness='1' dashed ='0' dashLen ='1' dashGap ='3' /><category showLabel='0' label='22/03/2013' /><category showLabel='0' label='25/03/2013' /><vLine color='edebeb' thickness='1' dashed ='0' dashLen ='1' dashGap ='3' /><category showLabel='0' label='09/04/2013' /><vLine color='edebeb' thickness='1' dashed ='0' dashLen ='1' dashGap ='3' /><category showLabel='0' label='07/05/2013' /><category showLabel='0' label='20/05/2013' /><vLine color='edebeb' thickness='1' dashed ='0' dashLen ='1' dashGap ='3' /><category showLabel='0' label='03/06/2013' /><category showLabel='0' label='13/06/2013' /><category showLabel='0' label='14/06/2013' /><category showLabel='0' label='25/06/2013' /><vLine color='edebeb' thickness='1' dashed ='0' dashLen ='1' dashGap ='3' /><category showLabel='0' label='24/07/2013' /><vLine color='edebeb' thickness='1' dashed ='0' dashLen ='1' dashGap ='3' /><category showLabel='0' label='05/08/2013' /><category showLabel='0' label='13/08/2013' /><vLine color='edebeb' thickness='1' dashed ='0' dashLen ='1' dashGap ='3' /><category showLabel='0' label='02/09/2013' /><category showLabel='0' label='03/09/2013' /><category showLabel='0' label='11/09/2013' /><category showLabel='0' label='20/09/2013' /><vLine color='edebeb' thickness='1' dashed ='0' dashLen ='1' dashGap ='3' /><category showLabel='0' label='10/10/2013' /><category showLabel='0' label='21/10/2013' /><vLine color='edebeb' thickness='1' dashed ='0' dashLen ='1' dashGap ='3' /><category showLabel='0' label='22/11/2013' /><category showLabel='0' label='25/11/2013' /><vLine color='edebeb' thickness='1' dashed ='0' dashLen ='1' dashGap ='3' /><category showLabel='0' label='06/12/2013' /><category showLabel='0' label='20/12/2013' /><category showLabel='0' label='30/12/2013' /><vLine color='c6c6c6' thickness='1' dashed ='0' dashLen ='1' dashGap ='3' /><category showLabel='1' label='2014' /><vLine color='edebeb' thickness='1' dashed ='0' dashLen ='1' dashGap ='3' /><category showLabel='0' label='11/02/2014' /><category showLabel='0' label='12/02/2014' /><vLine color='edebeb' thickness='1' dashed ='0' dashLen ='1' dashGap ='3' /><category showLabel='0' label='04/03/2014' /><category showLabel='0' label='10/03/2014' /><category showLabel='0' label='17/03/2014' /><vLine color='edebeb' thickness='1' dashed ='0' dashLen ='1' dashGap ='3' /><category showLabel='0' label='15/04/2014' /><vLine color='edebeb' thickness='1' dashed ='0' dashLen ='1' dashGap ='3' /><category showLabel='0' label='02/05/2014' /><category showLabel='0' label='05/05/2014' /><category showLabel='0' label='15/05/2014' /><vLine color='edebeb' thickness='1' dashed ='0' dashLen ='1' dashGap ='3' /><category showLabel='0' label='20/06/2014' /><category showLabel='0' label='24/06/2014' /><vLine color='edebeb' thickness='1' dashed ='0' dashLen ='1' dashGap ='3' /><category showLabel='0' label='03/07/2014' /><category showLabel='0' label='24/07/2014' /><category showLabel='0' label='25/07/2014' /><vLine color='edebeb' thickness='1' dashed ='0' dashLen ='1' dashGap ='3' /><category showLabel='0' label='07/08/2014' /><vLine color='edebeb' thickness='1' dashed ='0' dashLen ='1' dashGap ='3' /><category showLabel='0' label='09/09/2014' /><category showLabel='0' label='12/09/2014' /><category showLabel='0' label='24/09/2014' /><vLine color='edebeb' thickness='1' dashed ='0' dashLen ='1' dashGap ='3' /><category showLabel='0' label='13/10/2014' /><category showLabel='0' label='14/10/2014' /><category showLabel='0' label='15/10/2014' /><vLine color='edebeb' thickness='1' dashed ='0' dashLen ='1' dashGap ='3' /><category showLabel='0' label='13/11/2014' /><vLine color='edebeb' thickness='1' dashed ='0' dashLen ='1' dashGap ='3' /><category showLabel='0' label='09/12/2014' /><category showLabel='0' label='24/12/2014' /><vLine color='c6c6c6' thickness='1' dashed ='0' dashLen ='1' dashGap ='3' /><category showLabel='1' label='2015' /><category showLabel='0' label='05/01/2015' /><category showLabel='0' label='07/01/2015' /><vLine color='edebeb' thickness='1' dashed ='0' dashLen ='1' dashGap ='3' /><category showLabel='0' label='06/02/2015' /><vLine color='edebeb' thickness='1' dashed ='0' dashLen ='1' dashGap ='3' /><category showLabel='0' label='02/03/2015' /><category showLabel='0' label='19/03/2015' /><category showLabel='0' label='24/03/2015' /><category showLabel='0' label='25/03/2015' /><category showLabel='0' label='27/03/2015' /><vLine color='edebeb' thickness='1' dashed ='0' dashLen ='1' dashGap ='3' /><category showLabel='0' label='14/04/2015' /><vLine color='edebeb' thickness='1' dashed ='0' dashLen ='1' dashGap ='3' /><category showLabel='0' label='19/05/2015' /><vLine color='edebeb' thickness='1' dashed ='0' dashLen ='1' dashGap ='3' /><category showLabel='0' label='11/06/2015' /><category showLabel='0' label='12/06/2015' /><category showLabel='0' label='15/06/2015' /><category showLabel='0' label='26/06/2015' /><vLine color='edebeb' thickness='1' dashed ='0' dashLen ='1' dashGap ='3' /><category showLabel='0' label='16/07/2015' /><vLine color='edebeb' thickness='1' dashed ='0' dashLen ='1' dashGap ='3' /><category showLabel='0' label='10/08/2015' /><category showLabel='0' label='24/08/2015' /><vLine color='edebeb' thickness='1' dashed ='0' dashLen ='1' dashGap ='3' /><category showLabel='0' label='03/09/2015' /><category showLabel='0' label='04/09/2015' /><category showLabel='0' label='24/09/2015' /><vLine color='edebeb' thickness='1' dashed ='0' dashLen ='1' dashGap ='3' /><category showLabel='0' label='01/10/2015' /><category showLabel='0' label='23/10/2015' /><category showLabel='0' label='29/10/2015' /><vLine color='edebeb' thickness='1' dashed ='0' dashLen ='1' dashGap ='3' /><category showLabel='0' label='23/11/2015' /><category showLabel='0' label='24/11/2015' /><vLine color='edebeb' thickness='1' dashed ='0' dashLen ='1' dashGap ='3' /><category showLabel='0' label='01/12/2015' /><category showLabel='0' label='14/12/2015' /><vLine color='c6c6c6' thickness='1' dashed ='0' dashLen ='1' dashGap ='3' /><category showLabel='1' label='2016' /><category showLabel='0' label='11/02/2016' /><category showLabel='0' label='12/02/2016' /><category showLabel='0' label='15/02/2016' /><vLine color='edebeb' thickness='1' dashed ='0' dashLen ='1' dashGap ='3' /><category showLabel='0' label='03/03/2016' /><vLine color='edebeb' thickness='1' dashed ='0' dashLen ='1' dashGap ='3' /><category showLabel='0' label='07/04/2016' /><category showLabel='0' label='27/04/2016' /><category showLabel='0' label='28/04/2016' /><vLine color='edebeb' thickness='1' dashed ='0' dashLen ='1' dashGap ='3' /><category showLabel='0' label='03/05/2016' /><category showLabel='0' label='04/05/2016' /><vLine color='edebeb' thickness='1' dashed ='0' dashLen ='1' dashGap ='3' /><category showLabel='0' label='07/06/2016' /><category showLabel='0' label='29/06/2016' /><vLine color='edebeb' thickness='1' dashed ='0' dashLen ='1' dashGap ='3' /><category showLabel='0' label='01/07/2016' /><category showLabel='0' label='05/07/2016' /><category showLabel='0' label='22/07/2016' /><category showLabel='0' label='25/07/2016' /><vLine color='edebeb' thickness='1' dashed ='0' dashLen ='1' dashGap ='3' /><category showLabel='0' label='09/09/2016' /><category showLabel='0' label='14/09/2016' /><category showLabel='0' label='16/09/2016' /><vLine color='edebeb' thickness='1' dashed ='0' dashLen ='1' dashGap ='3' /><category showLabel='0' label='10/10/2016' /><category showLabel='0' label='12/10/2016' /><category showLabel='0' label='13/10/2016' /><category showLabel='0' label='25/10/2016' /><vLine color='edebeb' thickness='1' dashed ='0' dashLen ='1' dashGap ='3' /><category showLabel='0' label='04/11/2016' /><category showLabel='0' label='21/11/2016' /><vLine color='edebeb' thickness='1' dashed ='0' dashLen ='1' dashGap ='3' /><category showLabel='0' label='20/12/2016' /><vLine color='c6c6c6' thickness='1' dashed ='0' dashLen ='1' dashGap ='3' /><category showLabel='1' label='2017' /><category showLabel='0' label='03/01/2017' /><category showLabel='0' label='12/01/2017' /><vLine color='edebeb' thickness='1' dashed ='0' dashLen ='1' dashGap ='3' /><category showLabel='0' label='01/03/2017' /><category showLabel='0' label='17/03/2017' /><category showLabel='0' label='22/03/2017' /><category showLabel='0' label='24/03/2017' /><category showLabel='0' label='27/03/2017' /><vLine color='edebeb' thickness='1' dashed ='0' dashLen ='1' dashGap ='3' /><category showLabel='0' label='12/04/2017' /><vLine color='edebeb' thickness='1' dashed ='0' dashLen ='1' dashGap ='3' /><category showLabel='0' label='09/05/2017' /><category showLabel='0' label='23/05/2017' /><vLine color='edebeb' thickness='1' dashed ='0' dashLen ='1' dashGap ='3' /><category showLabel='0' label='12/06/2017' /><category showLabel='0' label='13/06/2017' /><category showLabel='0' label='14/06/2017' /><vLine color='edebeb' thickness='1' dashed ='0' dashLen ='1' dashGap ='3' /><category showLabel='0' label='18/07/2017' /><category showLabel='0' label='26/07/2017' /><vLine color='edebeb' thickness='1' dashed ='0' dashLen ='1' dashGap ='3' /><category showLabel='0' label='10/08/2017' /><category showLabel='0' label='29/08/2017' /><vLine color='edebeb' thickness='1' dashed ='0' dashLen ='1' dashGap ='3' /><category showLabel='0' label='01/09/2017' /><category showLabel='0' label='04/09/2017' /><category showLabel='0' label='20/09/2017' /><category showLabel='0' label='25/09/2017' /><vLine color='edebeb' thickness='1' dashed ='0' dashLen ='1' dashGap ='3' /><category showLabel='0' label='11/10/2017' /><vLine color='edebeb' thickness='1' dashed ='0' dashLen ='1' dashGap ='3' /><category showLabel='0' label='10/11/2017' /><category showLabel='0' label='22/11/2017' /><category showLabel='0' label='23/11/2017' /><vLine color='edebeb' thickness='1' dashed ='0' dashLen ='1' dashGap ='3' /><category showLabel='0' label='08/12/2017' /><category showLabel='0' label='21/12/2017' /><vLine color='c6c6c6' thickness='1' dashed ='0' dashLen ='1' dashGap ='3' /><category showLabel='1' label='2018' /><vLine color='edebeb' thickness='1' dashed ='0' dashLen ='1' dashGap ='3' /><category showLabel='0' label='09/02/2018' /><category showLabel='0' label='15/02/2018' /></categories><dataset seriesName='' ><set value='12.3319' toolText=' 02/01/2007 12.3319' /><set value='12.4052' toolText=' 03/01/2007 12.4052' /><set value='12.253' toolText=' 12/01/2007 12.253' /><set value='11.5313' toolText=' 23/01/2007 11.5313' /><set value='11.3113' toolText=' 05/03/2007 11.3113' /><set value='12.2924' toolText=' 23/03/2007 12.2924' /><set value='12.3489' toolText=' 26/03/2007 12.3489' /><set value='12.1064' toolText=' 28/03/2007 12.1064' /><set value='12.4481' toolText=' 09/05/2007 12.4481' /><set value='12.3404' toolText=' 11/05/2007 12.3404' /><set value='13.2432' toolText=' 05/06/2007 13.2432' /><set value='12.5616' toolText=' 13/06/2007 12.5616' /><set value='12.7948' toolText=' 14/06/2007 12.7948' /><set value='12.9322' toolText=' 15/06/2007 12.9322' /><set value='12.2089' toolText=' 26/06/2007 12.2089' /><set value='11.7665' toolText=' 06/08/2007 11.7665' /><set value='11.2762' toolText=' 16/08/2007 11.2762' /><set value='11.6588' toolText=' 31/08/2007 11.6588' /><set value='11.5752' toolText=' 03/09/2007 11.5752' /><set value='11.2524' toolText=' 06/09/2007 11.2524' /><set value='11.2105' toolText=' 20/09/2007 11.2105' /><set value='11.0073' toolText=' 28/09/2007 11.0073' /><set value='11.868' toolText=' 31/10/2007 11.868' /><set value='10.5467' toolText=' 22/11/2007 10.5467' /><set value='10.6903' toolText=' 23/11/2007 10.6903' /><set value='11.3479' toolText=' 07/12/2007 11.3479' /><set value='10.756' toolText=' 18/12/2007 10.756' /><set value='9.2315' toolText=' 11/01/2008 9.2315' /><set value='8.9983' toolText=' 16/01/2008 8.9983' /><set value='8.2029' toolText=' 11/02/2008 8.2029' /><set value='8.3763' toolText=' 12/02/2008 8.3763' /><set value='8.8248' toolText=' 26/02/2008 8.8248' /><set value='7.7068' toolText=' 31/03/2008 7.7068' /><set value='7.928' toolText=' 25/04/2008 7.928' /><set value='7.8024' toolText=' 29/04/2008 7.8024' /><set value='8.2509' toolText=' 02/05/2008 8.2509' /><set value='8.5499' toolText=' 05/05/2008 8.5499' /><set value='5.3538' toolText=' 20/06/2008 5.3538' /><set value='5.1164' toolText=' 24/06/2008 5.1164' /><set value='4.9845' toolText=' 02/07/2008 4.9845' /><set value='5.169' toolText=' 04/07/2008 5.169' /><set value='5.9604' toolText=' 23/07/2008 5.9604' /><set value='5.7692' toolText=' 24/07/2008 5.7692' /><set value='6.1977' toolText=' 12/08/2008 6.1977' /><set value='5.6637' toolText=' 21/08/2008 5.6637' /><set value='5.9604' toolText=' 02/09/2008 5.9604' /><set value='5.2352' toolText=' 15/09/2008 5.2352' /><set value='3.7978' toolText=' 10/10/2008 3.7978' /><set value='4.2196' toolText=' 13/10/2008 4.2196' /><set value='3.8044' toolText=' 16/10/2008 3.8044' /><set value='4.2856' toolText=' 23/10/2008 4.2856' /><set value='4.0746' toolText=' 19/11/2008 4.0746' /><set value='5.4064' toolText=' 10/12/2008 5.4064' /><set value='4.9779' toolText=' 30/12/2008 4.9779' /><set value='5.169' toolText=' 02/01/2009 5.169' /><set value='5.4792' toolText=' 06/01/2009 5.4792' /><set value='4.0088' toolText=' 03/02/2009 4.0088' /><set value='3.4352' toolText=' 03/03/2009 3.4352' /><set value='2.9407' toolText=' 12/03/2009 2.9407' /><set value='3.2108' toolText=' 23/03/2009 3.2108' /><set value='3.455' toolText=' 24/03/2009 3.455' /><set value='3.2769' toolText=' 30/03/2009 3.2769' /><set value='5.1955' toolText=' 15/04/2009 5.1955' /><set value='5.5317' toolText=' 12/05/2009 5.5317' /><set value='5.3256' toolText=' 26/05/2009 5.3256' /><set value='5.3183' toolText=' 12/06/2009 5.3183' /><set value='5.3478' toolText=' 15/06/2009 5.3478' /><set value='4.9336' toolText=' 18/06/2009 4.9336' /><set value='4.2235' toolText=' 08/07/2009 4.2235' /><set value='6.0507' toolText=' 14/08/2009 6.0507' /><set value='5.9396' toolText=' 18/08/2009 5.9396' /><set value='5.5993' toolText=' 02/09/2009 5.5993' /><set value='5.6956' toolText=' 03/09/2009 5.6956' /><set value='7.0343' toolText=' 17/09/2009 7.0343' /><set value='6.4019' toolText=' 08/10/2009 6.4019' /><set value='6.4351' toolText=' 12/10/2009 6.4351' /><set value='5.1962' toolText=' 03/11/2009 5.1962' /><set value='5.6215' toolText=' 20/11/2009 5.6215' /><set value='5.714' toolText=' 23/11/2009 5.714' /><set value='5.4626' toolText=' 26/11/2009 5.4626' /><set value='5.7176' toolText=' 08/12/2009 5.7176' /><set value='6.6941' toolText=' 15/12/2009 6.6941' /><set value='8.0699' toolText=' 03/02/2010 8.0699' /><set value='7.2487' toolText=' 11/02/2010 7.2487' /><set value='7.1379' toolText=' 12/02/2010 7.1379' /><set value='7.0047' toolText=' 25/02/2010 7.0047' /><set value='7.7629' toolText=' 08/03/2010 7.7629' /><set value='9.2781' toolText=' 09/04/2010 9.2781' /><set value='8.5202' toolText=' 26/04/2010 8.5202' /><set value='8.049' toolText=' 03/05/2010 8.049' /><set value='7.3718' toolText=' 04/05/2010 7.3718' /><set value='7.7549' toolText=' 12/05/2010 7.7549' /><set value='6.2604' toolText=' 18/06/2010 6.2604' /><set value='6.2643' toolText=' 23/06/2010 6.2643' /><set value='5.1913' toolText=' 01/07/2010 5.1913' /><set value='6.7483' toolText=' 23/07/2010 6.7483' /><set value='6.8615' toolText=' 26/07/2010 6.8615' /><set value='7.1819' toolText=' 28/07/2010 7.1819' /><set value='6.6308' toolText=' 30/07/2010 6.6308' /><set value='5.6271' toolText=' 25/08/2010 5.6271' /><set value='5.8231' toolText=' 30/08/2010 5.8231' /><set value='6.4618' toolText=' 13/10/2010 6.4618' /><set value='6.4693' toolText=' 14/10/2010 6.4693' /><set value='7.0122' toolText=' 12/11/2010 7.0122' /><set value='6.0847' toolText=' 30/11/2010 6.0847' /><set value='7.3771' toolText=' 10/12/2010 7.3771' /><set value='6.9789' toolText=' 29/12/2010 6.9789' /><set value='6.8579' toolText=' 30/12/2010 6.8579' /><set value='6.9629' toolText=' 03/01/2011 6.9629' /><set value='6.7938' toolText=' 10/01/2011 6.7938' /><set value='7.3879' toolText=' 12/01/2011 7.3879' /><set value='8.3029' toolText=' 09/02/2011 8.3029' /><set value='7.6663' toolText=' 25/02/2011 7.6663' /><set value='7.0279' toolText=' 24/03/2011 7.0279' /><set value='7.0521' toolText=' 25/03/2011 7.0521' /><set value='7.1071' toolText=' 29/03/2011 7.1071' /><set value='6.8247' toolText=' 08/04/2011 6.8247' /><set value='6.3647' toolText=' 02/05/2011 6.3647' /><set value='5.656' toolText=' 09/05/2011 5.656' /><set value='5.0671' toolText=' 13/06/2011 5.0671' /><set value='5.1195' toolText=' 14/06/2011 5.1195' /><set value='5.0346' toolText=' 15/06/2011 5.0346' /><set value='5.0828' toolText=' 06/07/2011 5.0828' /><set value='5.7155' toolText=' 29/07/2011 5.7155' /><set value='4.1022' toolText=' 26/08/2011 4.1022' /><set value='4.2456' toolText=' 02/09/2011 4.2456' /><set value='3.9816' toolText=' 05/09/2011 3.9816' /><set value='3.5045' toolText=' 22/09/2011 3.5045' /><set value='3.5298' toolText=' 04/10/2011 3.5298' /><set value='4.0009' toolText=' 11/10/2011 4.0009' /><set value='4.4291' toolText=' 27/10/2011 4.4291' /><set value='3.3585' toolText=' 22/11/2011 3.3585' /><set value='3.286' toolText=' 23/11/2011 3.286' /><set value='3.2843' toolText=' 24/11/2011 3.2843' /><set value='3.4729' toolText=' 28/11/2011 3.4729' /><set value='3.8575' toolText=' 20/12/2011 3.8575' /><set value='4.318' toolText=' 06/02/2012 4.318' /><set value='4.0724' toolText=' 10/02/2012 4.0724' /><set value='3.9939' toolText=' 13/02/2012 3.9939' /><set value='3.7543' toolText=' 15/02/2012 3.7543' /><set value='3.9449' toolText=' 20/02/2012 3.9449' /><set value='4.1171' toolText=' 19/03/2012 4.1171' /><set value='3.1077' toolText=' 30/04/2012 3.1077' /><set value='3.1548' toolText=' 03/05/2012 3.1548' /><set value='3.0768' toolText=' 04/05/2012 3.0768' /><set value='2.9917' toolText=' 09/05/2012 2.9917' /><set value='3.2672' toolText=' 14/05/2012 3.2672' /><set value='3.3543' toolText=' 13/06/2012 3.3543' /><set value='3.6579' toolText=' 15/06/2012 3.6579' /><set value='3.4458' toolText=' 23/07/2012 3.4458' /><set value='3.4168' toolText=' 24/07/2012 3.4168' /><set value='3.3478' toolText=' 25/07/2012 3.3478' /><set value='3.3533' toolText=' 02/08/2012 3.3533' /><set value='3.7874' toolText=' 13/08/2012 3.7874' /><set value='4.2134' toolText=' 21/09/2012 4.2134' /><set value='3.5346' toolText=' 12/10/2012 3.5346' /><set value='3.5808' toolText=' 15/10/2012 3.5808' /><set value='3.7621' toolText=' 25/10/2012 3.7621' /><set value='3.8437' toolText=' 29/10/2012 3.8437' /><set value='3.859' toolText=' 28/11/2012 3.859' /><set value='5.1568' toolText=' 19/12/2012 5.1568' /><set value='4.613' toolText=' 31/12/2012 4.613' /><set value='4.8968' toolText=' 02/01/2013 4.8968' /><set value='5.2674' toolText=' 25/01/2013 5.2674' /><set value='5.3091' toolText=' 30/01/2013 5.3091' /><set value='4.5587' toolText=' 07/02/2013 4.5587' /><set value='4.9846' toolText=' 25/02/2013 4.9846' /><set value='5.2211' toolText=' 22/03/2013 5.2211' /><set value='5.2112' toolText=' 25/03/2013 5.2112' /><set value='4.8487' toolText=' 09/04/2013 4.8487' /><set value='5.6499' toolText=' 07/05/2013 5.6499' /><set value='6.0631' toolText=' 20/05/2013 6.0631' /><set value='5.3154' toolText=' 03/06/2013 5.3154' /><set value='5.4958' toolText=' 13/06/2013 5.4958' /><set value='5.6852' toolText=' 14/06/2013 5.6852' /><set value='5.4658' toolText=' 25/06/2013 5.4658' /><set value='7.1598' toolText=' 24/07/2013 7.1598' /><set value='7.2504' toolText=' 05/08/2013 7.2504' /><set value='7.1843' toolText=' 13/08/2013 7.1843' /><set value='6.761' toolText=' 02/09/2013 6.761' /><set value='6.8607' toolText=' 03/09/2013 6.8607' /><set value='7.1706' toolText=' 11/09/2013 7.1706' /><set value='7.2232' toolText=' 20/09/2013 7.2232' /><set value='8.124' toolText=' 10/10/2013 8.124' /><set value='8.5192' toolText=' 21/10/2013 8.5192' /><set value='7.5667' toolText=' 22/11/2013 7.5667' /><set value='7.864' toolText=' 25/11/2013 7.864' /><set value='7.3266' toolText=' 06/12/2013 7.3266' /><set value='7.5087' toolText=' 20/12/2013 7.5087' /><set value='7.5948' toolText=' 30/12/2013 7.5948' /><set value='8.4041' toolText=' 21/01/2014 8.4041' /><set value='8.2147' toolText=' 11/02/2014 8.2147' /><set value='8.135' toolText=' 12/02/2014 8.135' /><set value='7.8893' toolText=' 04/03/2014 7.8893' /><set value='8.2356' toolText=' 10/03/2014 8.2356' /><set value='7.7996' toolText=' 17/03/2014 7.7996' /><set value='6.9794' toolText=' 15/04/2014 6.9794' /><set value='7.1969' toolText=' 02/05/2014 7.1969' /><set value='7.0601' toolText=' 05/05/2014 7.0601' /><set value='6.7148' toolText=' 15/05/2014 6.7148' /><set value='7.7244' toolText=' 20/06/2014 7.7244' /><set value='7.6836' toolText=' 24/06/2014 7.6836' /><set value='7.9809' toolText=' 03/07/2014 7.9809' /><set value='8.2655' toolText=' 24/07/2014 8.2655' /><set value='8.2237' toolText=' 25/07/2014 8.2237' /><set value='7.399' toolText=' 07/08/2014 7.399' /><set value='8.4014' toolText=' 09/09/2014 8.4014' /><set value='9.0558' toolText=' 12/09/2014 9.0558' /><set value='8.7422' toolText=' 24/09/2014 8.7422' /><set value='8.1413' toolText=' 13/10/2014 8.1413' /><set value='8.1403' toolText=' 14/10/2014 8.1403' /><set value='7.7588' toolText=' 15/10/2014 7.7588' /><set value='8.3987' toolText=' 13/11/2014 8.3987' /><set value='9.1491' toolText=' 09/12/2014 9.1491' /><set value='9.6068' toolText=' 24/12/2014 9.6068' /><set value='9.5116' toolText=' 02/01/2015 9.5116' /><set value='9.2805' toolText=' 05/01/2015 9.2805' /><set value='9.0331' toolText=' 07/01/2015 9.0331' /><set value='9.6974' toolText=' 06/02/2015 9.6974' /><set value='10.0328' toolText=' 02/03/2015 10.0328' /><set value='10.2004' toolText=' 19/03/2015 10.2004' /><set value='10.5312' toolText=' 24/03/2015 10.5312' /><set value='10.3544' toolText=' 25/03/2015 10.3544' /><set value='10.3091' toolText=' 27/03/2015 10.3091' /><set value='11.1293' toolText=' 14/04/2015 11.1293' /><set value='11.296' toolText=' 19/05/2015 11.296' /><set value='10.9341' toolText=' 11/06/2015 10.9341' /><set value='10.902' toolText=' 12/06/2015 10.902' /><set value='10.8104' toolText=' 15/06/2015 10.8104' /><set value='11.2456' toolText=' 26/06/2015 11.2456' /><set value='11.9969' toolText=' 16/07/2015 11.9969' /><set value='10.389' toolText=' 10/08/2015 10.389' /><set value='9.1797' toolText=' 24/08/2015 9.1797' /><set value='9.7202' toolText=' 03/09/2015 9.7202' /><set value='9.5278' toolText=' 04/09/2015 9.5278' /><set value='8.915' toolText=' 24/09/2015 8.915' /><set value='8.8755' toolText=' 01/10/2015 8.8755' /><set value='9.7981' toolText=' 23/10/2015 9.7981' /><set value='10.215' toolText=' 29/10/2015 10.215' /><set value='9.7294' toolText=' 23/11/2015 9.7294' /><set value='9.6195' toolText=' 24/11/2015 9.6195' /><set value='10.0454' toolText=' 01/12/2015 10.0454' /><set value='9.2438' toolText=' 14/12/2015 9.2438' /><set value='7.9713' toolText=' 03/02/2016 7.9713' /><set value='7.5673' toolText=' 11/02/2016 7.5673' /><set value='7.5756' toolText=' 12/02/2016 7.5756' /><set value='7.7184' toolText=' 15/02/2016 7.7184' /><set value='9.4453' toolText=' 03/03/2016 9.4453' /><set value='9.0789' toolText=' 07/04/2016 9.0789' /><set value='10.9534' toolText=' 27/04/2016 10.9534' /><set value='10.8622' toolText=' 28/04/2016 10.8622' /><set value='10.699' toolText=' 03/05/2016 10.699' /><set value='10.627' toolText=' 04/05/2016 10.627' /><set value='11.5294' toolText=' 07/06/2016 11.5294' /><set value='9.5278' toolText=' 29/06/2016 9.5278' /><set value='9.8158' toolText=' 01/07/2016 9.8158' /><set value='9.1966' toolText=' 05/07/2016 9.1966' /><set value='10.1086' toolText=' 22/07/2016 10.1086' /><set value='10.2046' toolText=' 25/07/2016 10.2046' /><set value='10.7518' toolText=' 09/09/2016 10.7518' /><set value='10.2094' toolText=' 14/09/2016 10.2094' /><set value='10.1278' toolText=' 16/09/2016 10.1278' /><set value='9.7438' toolText=' 10/10/2016 9.7438' /><set value='9.7726' toolText=' 12/10/2016 9.7726' /><set value='9.5902' toolText=' 13/10/2016 9.5902' /><set value='10.0222' toolText=' 25/10/2016 10.0222' /><set value='9.2158' toolText=' 04/11/2016 9.2158' /><set value='9.068' toolText=' 21/11/2016 9.068' /><set value='11.0062' toolText=' 20/12/2016 11.0062' /><set value='10.7758' toolText=' 02/01/2017 10.7758' /><set value='10.7422' toolText=' 03/01/2017 10.7422' /><set value='10.459' toolText=' 12/01/2017 10.459' /><set value='11.0254' toolText=' 01/03/2017 11.0254' /><set value='11.3086' toolText=' 17/03/2017 11.3086' /><set value='11.155' toolText=' 22/03/2017 11.155' /><set value='11.3902' toolText=' 24/03/2017 11.3902' /><set value='11.4046' toolText=' 27/03/2017 11.4046' /><set value='11.7982' toolText=' 12/04/2017 11.7982' /><set value='12.62' toolText=' 09/05/2017 12.62' /><set value='11.875' toolText=' 23/05/2017 11.875' /><set value='11.29' toolText=' 12/06/2017 11.29' /><set value='11.36' toolText=' 13/06/2017 11.36' /><set value='11.315' toolText=' 14/06/2017 11.315' /><set value='10.47' toolText=' 18/07/2017 10.47' /><set value='10.565' toolText=' 26/07/2017 10.565' /><set value='10.665' toolText=' 10/08/2017 10.665' /><set value='9.648' toolText=' 29/08/2017 9.648' /><set value='9.513' toolText=' 01/09/2017 9.513' /><set value='9.499' toolText=' 04/09/2017 9.499' /><set value='9.57' toolText=' 20/09/2017 9.57' /><set value='9.644' toolText=' 25/09/2017 9.644' /><set value='9.532' toolText=' 11/10/2017 9.532' /><set value='8.615' toolText=' 10/11/2017 8.615' /><set value='9.185' toolText=' 22/11/2017 9.185' /><set value='9.309' toolText=' 23/11/2017 9.309' /><set value='9.89' toolText=' 08/12/2017 9.89' /><set value='9.84' toolText=' 21/12/2017 9.84' /><set value='9.35' toolText=' 18/01/2018 9.35' /><set value='8.694' toolText=' 09/02/2018 8.694' /><set value='9.262' toolText=' 15/02/2018 9.262' /></dataset><styles>

      <definition>
         <!-- <style name='CanvasAnim' type='animation' param='_yScale' start='0' duration='1' Easing='Bounce'/> -->
		 <!-- <style name='myAnim' type='animation'   param='_alpha' start='0' duration='1' />-->
		 <style name='myValuesFont' type='font' size='16'  bold='1' isHTML='1'/>
		 <style name='myTrendValuesFont' type='font' isHTML='1'/>
		 <style name='MyFirstShadow' type='Shadow'  Color= '999999' distance='3'  Alpha= '50' angle='90' blurY='3' blurX='3' />
		 <style name='lineas' type='ANIMATION' duration='1' start='0' param='_alpha' />
		 <style name='myToolTipFont' type='font' font='Arial' size='10' color='4E4E4E'/>
		 <style name='myToolTipFont' type='font' font='Arial' size='12' color='616161'/>
		 <style name='myLegendFont' type='font' size='12' color='808080' bold='1' />
		
      </definition>

      <application>
		 <apply toObject='DataValues' styles='myValuesFont' />
		 <apply toObject='DataPlot' styles='MyFirstShadow' />
		 <apply toObject='DivLines' styles='lineas' />
		 <apply toObject='ToolTip' styles='myToolTipFont' />
		 <apply toObject='Legend' styles='myLegendFont' />
		 <apply toObject='TrendValues' styles='myTrendValuesFont' />
      </application>   

   </styles></chart>